Workbook
Name AmortYrs: 'مصاريف ما قبل التشغيل'!$B$12
Name AssayCost: الافتراضات!$B$51
Name AvailFactor: الافتراضات!$B$18
Name BankGuar: الافتراضات!$B$34
Name BenchGrade: الافتراضات!$B$22
Name BrkProd: الافتراضات!$B$19
Name CifBench: الافتراضات!$B$21
Name CommunityRate: الافتراضات!$B$32
Name DieselPrice: الافتراضات!$B$46
Name DiscRate: الافتراضات!$B$59
Name EosRate: الافتراضات!$B$39
Name EqIns: الافتراضات!$B$48
Name ExpIns: الافتراضات!$B$40
Name F_Capex: 'تحليل الحساسية'!$B$8
Name F_Opex: 'تحليل الحساسية'!$B$7
Name F_Price: 'تحليل الحساسية'!$B$5
Name F_Vol: 'تحليل الحساسية'!$B$6
Name FxRate: الافتراضات!$B$9
Name GenAdmin: الافتراضات!$B$49
Name GuarComm: الافتراضات!$B$35
Name HaulDist: الافتراضات!$B$26
Name InflRate: الافتراضات!$B$47
Name K_IRR: 'المؤشرات المالية'!$B$7
Name K_IRRNew: 'المؤشرات المالية'!$B$13
Name K_NPV: 'المؤشرات المالية'!$B$6
Name K_NPVNew: 'المؤشرات المالية'!$B$12
Name K_Payback: 'المؤشرات المالية'!$B$8
Name LocalPrice: 'السوق والسعر'!$B$38
Name LocalShare: 'السوق والسعر'!$B$39
Name LicFees: التراخيص!$D$10
Name LicRenew: الافتراضات!$B$53
Name Loan: الافتراضات!$B$55
Name LoanRate: الافتراضات!$B$56
Name LoanYrs: الافتراضات!$B$57
Name MinExportGrade: 'السوق والسعر'!$B$13
Name MinWage: الافتراضات!$B$44
Name NatAvgOutput: 'السوق والسعر'!$B$11
Name NatAvgPrice: 'السوق والسعر'!$B$9
Name NewInv: 'التكلفة الاستثمارية والتمويل'!$B$12
Name OreGrade: الافتراضات!$B$13
Name OreReserve: الافتراضات!$B$12
Name Payroll: 'الموارد البشرية'!$G$17
Name Permit2: الافتراضات!$B$41
Name Permit3: الافتراضات!$B$42
Name PermitCost: 'الموارد البشرية'!$B$42
Name PermitOther: الافتراضات!$B$43
Name PermitRenew: 'الموارد البشرية'!$B$40
Name PortCost: الافتراضات!$B$24
Name PreOp: 'مصاريف ما قبل التشغيل'!$B$10
Name PriceDisc: الافتراضات!$B$28
Name PriceG: الافتراضات!$B$29
Name RehabCost: الافتراضات!$B$52
Name RoyaltyRate: الافتراضات!$B$31
Name SalePrice: 'السوق والسعر'!$B$41
Name SeaFreight: الافتراضات!$B$23
Name ShiftHrs: الافتراضات!$B$17
Name SiteRent: الإيجارات!$E$9
Name SortRecov: الافتراضات!$B$15
Name SPFEx: الافتراضات!$B$38
Name SPFOm: الافتراضات!$B$37

Sheet الغلاف والفهرس
B2: دراسة الجدوى الاقتصادية والفنية
B3: مشروع استخراج خام الكروم (محجر كروم) — محافظة شمال الشرقية، سلطنة عُمان
B4: Chromite Quarry Project — Technical & Economic Feasibility Study (updated, fully linked model)
B5: تاريخ التحديث: أكتوبر 2026 — العملة: ريال عُماني (ر.ع) — مدة الدراسة: سنة تأسيس + 5 سنوات تشغيل
A7: م | B7: الورقة | C7: المحتوى
A8: 1 | B8: الملخص التنفيذي | C8: الملخص التنفيذي: أهم الأرقام والمؤشرات والخلاصة
A9: 2 | B9: الافتراضات | C9: جميع الافتراضات والمدخلات الرئيسية مع مصدر كل رقم وحالته
A10: 3 | B10: التراخيص | C10: التراخيص المطلوبة ورسومها والإطار التنظيمي للقطاع
A11: 4 | B11: السوق والسعر | C11: بيانات السوق والأسعار المرجعية، وبناء سعر التصدير، والبيع المحلي وسعر البيع المعتمد
A12: 5 | B12: الخطة الفنية والإنتاج | C12: الطاقة الإنتاجية وبرنامج الإنتاج السنوي واستنزاف الاحتياطي
A13: 6 | B13: الإنتاج الشهري | C13: توزيع الإنتاج على 60 شهراً حسب أيام العمل، مع مطابقة المجاميع السنوية
A14: 7 | B14: الجدول الزمني | C14: مراحل وخطة تنفيذ المشروع بالتسلسل الصحيح (مخطط زمني)
A15: 8 | B15: الأصول والإهلاك | C15: الأصول الثابتة وجدول الإهلاك والاستبدال
A16: 9 | B16: مصاريف ما قبل التشغيل | C16: مصاريف ما قبل التشغيل وإطفاؤها
A17: 10 | B17: الموارد البشرية | C17: الأجور والرواتب والتأمينات ومأذونيات العمل
A18: 11 | B18: الإيجارات | C18: إيجار المواقع والمعدات والمركبات
A19: 12 | B19: المواد المستهلكة | C19: الوقود والمواد المستهلكة
... A28: 21 | B28: التصحيحات والمصادر | C28: ما تم تصحيحه في الدراسة الأصلية، البنود التي تحتاج تأكيداً، والمصادر
B29: دليل الألوان
B30: 1000 | C30: خلية مدخلات (خط أزرق وخلفية صفراء): يمكن تعديلها، وكل النتائج تُعاد احتسابها تلقائياً
B31: 1000 | C31: خلية محتسبة بمعادلة (خط أسود): لا تُعدَّل
B32: 1000 | C32: إجمالي
B33: 1000 | C33: نتيجة رئيسية
B35: تنبيه مهم
C36: نتائج هذه الدراسة تعتمد على افتراضات جيولوجية وسوقية لم ترد في الملف الأصلي (الاحتياطي، درجة الخام، نسبة التعرية، سعر البيع). يجب استبدالها بالأرقام الفعلية من التقرير الاستكشافي وعقد البيع قبل تقديم الدراسة لأي جهة — انظر ورقة «التصحيحات والمصادر».

Sheet الملخص التنفيذي
A1: الملخص التنفيذي
A2: جميع الأرقام مرتبطة بأوراق الدراسة وتتحدّث تلقائياً عند تعديل الافتراضات
A4: المؤشر | B4: القيمة | C4: الوحدة | D4: ملاحظات
A5: أولاً: المشروع
A6: الطاقة الإنتاجية — خام قابل للبيع | B6: =SaleCap -> 60000 | C6: طن/سنة | D6: معطى من المالك — 60,000 طن صافٍ سنوياً
A7: متوسط درجة الخام | B7: =OreGrade -> 0.32 | C7: Cr2O3 | D7: افتراض — يُستبدل بنتائج المختبر
A8: سعر البيع عند موقع التجميع | B8: =SalePrice -> 38.66 | C8: ر.ع/طن | D8: ="بيع محلي "&TEXT(LocalShare,"0%")&" + تصدير "&TEXT(1-LocalShare,"0%")&" — متوسط مرجّح من ورقة «السوق والسعر»" -> بيع محلي 100% + تصدير 0% — متوسط مرجّح من ورقة «السوق والسعر»
A9: عدد العاملين | B9: ='الموارد البشرية'!D17 -> 18 | C9: عامل
A10: نسبة التعمين | B10: ='الموارد البشرية'!B22 -> 0.55555556 | C10: %
A11: ثانياً: الاستثمار والتمويل
A12: إجمالي التكلفة الاستثمارية | B12: =TotalInv -> 504507.54 | C12: ر.ع | D12: أصول ثابتة + ما قبل التشغيل + ضمانات بنكية + رأس مال عامل
A13: منها: مصاريف استكشاف مدفوعة سابقاً | B13: =SunkCost -> 200000 | C13: ر.ع | D13: مساهمة المالك المنفذة خلال السنوات الثلاث الماضية
A14: الاستثمار الجديد المطلوب | B14: =NewInv -> 304507.54 | C14: ر.ع
A15: القرض البنكي المفترض | B15: =Loan -> 150000 | C15: ر.ع | D15: افتراض — يُعدَّل حسب شروط الجهة الممولة
A16: ثالثاً: التشغيل في السنة الثالثة (منتصف مدة الدراسة)
A17: الإيرادات | B17: =الإيرادات!F7 -> 2319600 | C17: ر.ع
A18: التكاليف التشغيلية النقدية (شاملة الإتاوة) | B18: ='التكاليف التشغيلية'!F31 -> 537366.43 | C18: ر.ع
A19: تكلفة الطن المباع | B19: ='التكاليف التشغيلية'!F32 -> 8.9561071 | C19: ر.ع/طن
A20: الربح قبل الفوائد والضرائب والإهلاك (EBITDA) | B20: ='قائمة الدخل'!F10 -> 1782233.6 | C20: ر.ع
A21: صافي الربح بعد الضريبة | B21: ='قائمة الدخل'!F20 -> 1460010.8 | C21: ر.ع
A22: رابعاً: مؤشرات الجدوى
A23: صافي القيمة الحالية (NPV) | B23: =K_NPV -> 5125634.4 | C23: ر.ع | D23: على إجمالي الاستثمار شاملاً المصاريف السابقة، عند معدل الخصم المعتمد
A24: معدل العائد الداخلي (IRR) | B24: =K_IRR -> 3.097682 | C24: % | D24: على إجمالي الاستثمار
A25: معدل العائد الداخلي على الاستثمار الجديد فقط | B25: =K_IRRNew -> 5.1443895 | C25: % | D25: باستبعاد المصاريف المدفوعة سابقاً (تكلفة غارقة)
A26: فترة الاسترداد | B26: =K_Payback -> 0.32109921 | C26: سنة | D26: من بداية الإنتاج
A27: سعر التعادل | B27: ='المؤشرات المالية'!B29 -> 8.2050398 | C27: ر.ع/طن | D27: السعر الذي يغطي جميع التكاليف في سنة التشغيل الكامل
A28: نسبة التعادل من الطاقة الإنتاجية | B28: ='المؤشرات المالية'!B28 -> 0.10662057 | C28: %
A29: خامساً: الخلاصة
A30: =IF(AND(ISNUMBER(K_IRR),K_NPV>0),"النتيجة: المشروع مجدٍ اقتصادياً وفق الافتراضات الحالية — صافي القيمة الحالية موجب ومعدل العائد الداخلي أعلى من معدل الخصم.","النتيجة: المشروع غير مجدٍ وفق الافتراضات الحالية — صافي القيمة الحالية سالب عند معدل الخصم المعتمد.") -> النتيجة: المشروع مجدٍ اقتصادياً وفق الافتراضات الحالية — صافي القيمة الحالية موجب ومعدل العائد الداخلي أعلى من معدل الخصم.
A31: 1) الجدوى شديدة الحساسية لسعر البيع والكمية المباعة (نسبة التعرية ودرجة الخام) — انظر «تحليل الحساسية».
A32: 2) الاحتياطي والدرجة ونسبة التعرية افتراضات يجب استبدالها بنتائج التقرير الاستكشافي المعتمد.
A33: 3) القرار الوزاري 18/2025: التصدير حصري عبر شركة متاجرة المعادن، ولا يُصدَّر الخام غير المعالج بدرجة أقل من 36%.
A34: 4) تفاصيل ما تم تصحيحه والبنود التي تحتاج تأكيداً في ورقة «التصحيحات والمصادر».
A35: ="5) الحفارات: "&'الخطة الفنية والإنتاج'!C14&" — الاحتياطي: "&'الخطة الفنية والإنتاج'!B28 -> 5) الحفارات: كافية — المطلوب 86% من طاقة الحفارات — الاحتياطي: الاحتياطي المفترض كافٍ لخمس سنوات تشغيل

Sheet الافتراضات
A1: الافتراضات والمدخلات الرئيسية
A2: الخلايا الصفراء بخط أزرق مدخلات قابلة للتعديل. عمود «المصدر / الحالة» يبيّن: من الدراسة الأصلية — مصدر منشور — افتراض يحتاج تأكيداً
A4: البند | B4: القيمة | C4: الوحدة | D4: المصدر / الحالة
A5: أولاً: بيانات عامة
A6: اسم المشروع | B6: محجر خام الكروم | C6: — | D6: من الدراسة الأصلية
A7: الموقع | B7: محافظة شمال الشرقية | C7: — | D7: من الدراسة الأصلية (الترخيص البلدي صادر من بلدية شمال الشرقية) — يُستكمل اسم الولاية ورقم الموقع وإحداثياته
A8: تاريخ بدء التنفيذ | B8: 46388 | C8: تاريخ | D8: افتراض — يُستخدم في الجدول الزمني فقط
A9: سعر صرف الدولار الأمريكي | B9: 0.3845 | C9: ر.ع / دولار | D9: سعر الربط الرسمي (1 ر.ع = 2.6008 دولار)
A10: مدة التشغيل في الدراسة | B10: 5 | C10: سنة | D10: ثابتة في بنية النموذج (سنة تأسيس + 5 سنوات تشغيل)
A11: ثانياً: الاحتياطي والإنتاج
A12: الاحتياطي القابل للتعدين | B12: 400000 | C12: طن خام | D12: معطى من المالك (أكتوبر 2026) — يُوثَّق بالتقرير الاستكشافي المعتمد
A13: متوسط نسبة أكسيد الكروم في الخام (Cr2O3) | B13: 0.32 | C13: % | D13: افتراض يحتاج تأكيداً — يُستبدل بنتائج تحاليل المختبر. الخام العُماني المتداول عالمياً غالباً 30–32%
A14: نسبة التعرية (طن صخور عقيمة لكل طن خام) | B14: 4 | C14: طن / طن | D14: معطى من المالك (أكتوبر 2026) — يحدد حجم الصخور المطلوب تحريكها وكفاية الحفارات
A15: نسبة استرداد الخام بعد الفرز اليدوي | B15: 0.85 | C15: % | D15: افتراض (الدراسة الأصلية تتضمن 5 عمال فرز)
A16: أيام العمل في السنة | B16: 312 | C16: يوم | D16: معطى من المالك: 6 أيام في الأسبوع × 52 أسبوعاً
A17: ساعات العمل اليومية | B17: 10 | C17: ساعة | D17: معطى من المالك: 10 ساعات يومياً. يتجاوز 9 ساعات للعامل في قانون العمل — يلزم عمل إضافي مدفوع أو نظام ورديتين للعمالة الميدانية
A18: معامل جاهزية واستغلال المعدات | B18: 0.75 | C18: % | D18: افتراض: يشمل الأعطال والصيانة وتوقفات الطقس والتنقل
A19: إنتاجية الحفار في التكسير والتحميل (للتحقق من الطاقة) | B19: 35 | C19: طن صخر / ساعة | D19: افتراض لصخور البريدوتيت/الدونيت — يُستخدم فقط للتحقق من كفاية الحفارات المستأجرة
A20: ثالثاً: السوق والسعر
A21: السعر المرجعي CIF الصين — كروم عُماني كتل 30–32% | B21: 200 | C21: دولار / طن | D21: مصدر منشور: SMM — 192.5 دولار (17 يونيو 2026) و205 دولار (30 سبتمبر 2026)؛ اعتُمد متوسط مقرَّب
A22: درجة الخام المرجعي (منتصف النطاق) | B22: 0.31 | C22: % | D22: منتصف نطاق 30–32% — يُستخدم لتحويل السعر إلى سعر وحدة الكروم
A23: أجور الشحن البحري عُمان – الصين | B23: 24 | C23: دولار / طن | D23: افتراض يحتاج تأكيداً (شحن سائب)
A24: مناولة وتخزين وتحميل في الميناء | B24: 2.5 | C24: ر.ع / طن | D24: افتراض يحتاج تأكيداً
A25: هامش التسويق والفحص والتمويل (المشتري/المصدِّر) | B25: 0.1 | C25: % من سعر CIF | D25: افتراض يحتاج تأكيداً — لم تُنشر بعد آلية تسعير شركة متاجرة المعادن للمنتجين
A26: مسافة النقل البري من موقع التجميع إلى الميناء | B26: 300 | C26: كم | D26: افتراض يحتاج تأكيداً حسب الموقع الفعلي والميناء (صحار / صلالة / الدقم)
A27: تعرفة النقل البري | B27: 0.02 | C27: ر.ع / طن.كم | D27: افتراض يحتاج تأكيداً بعروض شركات النقل
A28: خصم تحوّطي على صافي السعر | B28: 0.12 | C28: % | D28: تحوّط لتقلب الأسعار وغرامات الجودة والرطوبة؛ يقرّب السعر من المتوسط الوطني المحقق فعلياً
A29: التغير السنوي في سعر البيع | B29: 0 | C29: % سنوياً | D29: افتراض متحفظ: ثبات السعر مع تضخم التكاليف
A30: رابعاً: الرسوم الحكومية والضرائب
A31: الإتاوة الحكومية | B31: 0.05 | C31: % من قيمة الإنتاج | D31: قانون الثروة المعدنية (م.س 19/2019): لا تقل عن 5% — تُؤكَّد النسبة المحددة في الترخيص
A32: مساهمة تنمية المجتمع المحلي | B32: 0.01 | C32: % من قيمة الإنتاج | D32: قانون الثروة المعدنية: لا تقل عن 1%
A33: ضريبة الدخل | B33: 0.15 | C33: % من الربح | D33: قانون ضريبة الدخل: 15% (نسبة 3% للمؤسسات الصغيرة لا تنطبق على استخراج الثروات الطبيعية)
A34: الضمانات البنكية (وزارة الطاقة والمعادن / هيئة البيئة) | B34: 55000 | C34: ر.ع | D34: من الدراسة الأصلية — عولجت كوديعة مستردة في نهاية المشروع لا كمصروف
A35: عمولة الضمان البنكي السنوية | B35: 0.015 | C35: % سنوياً | D35: افتراض يحتاج تأكيداً من البنك
A36: خامساً: العمالة
A37: اشتراك صاحب العمل في صندوق الحماية الاجتماعية — العمانيون | B37: 0.145 | C37: % من الأجر | D37: مصدر منشور: شيخوخة وعجز ووفاة 11% + إصابات عمل 1% + أمان وظيفي 0.5% + أمومة 1% + إجازات مرضية 1% (من يوليو 2026)
A38: اشتراكات صاحب العمل — الوافدون | B38: 0.03 | C38: % من الأجر | D38: أمومة 1% + إصابات عمل 1% + إجازات مرضية 1% — يُتحقق من الصندوق
A39: مخصص نهاية الخدمة / نظام الادخار للوافدين | B39: 0.09 | C39: % من الأجر | D39: نظام الادخار 9% اعتباراً من يوليو 2027 (وقبله مكافأة نهاية الخدمة: راتب شهر عن كل سنة)
A40: التأمين الصحي وتأمين العمال للوافد | B40: 400 | C40: ر.ع / عامل / سنة | D40: من الدراسة الأصلية (4,800 ÷ 12 عاملاً)
A41: رسوم مأذونية العمل — مهن الفئة الثانية | B41: 251 | C41: ر.ع / سنتين | D41: مصدر منشور: قرار وزارة العمل 602/2025 (صلاحية 24 شهراً)
A42: رسوم مأذونية العمل — مهن الفئة الثالثة | B42: 201 | C42: ر.ع / سنتين | D42: مصدر منشور: قرار وزارة العمل 602/2025
A43: مصاريف استقدام أخرى للوافد (فحص طبي، بطاقة مقيم، تأشيرة) | B43: 40 | C43: ر.ع / عامل | D43: افتراض
A44: الحد الأدنى لأجر العامل العُماني | B44: 325 | C44: ر.ع / شهر | D44: يُستخدم للتحقق من الرواتب في ورقة «الموارد البشرية»
A45: سادساً: التشغيل
A46: سعر الديزل | B46: 0.258 | C46: ر.ع / لتر | D46: مصدر منشور: سعر السوق المحلي، أكتوبر 2026
A47: التضخم السنوي للتكاليف | B47: 0.015 | C47: % سنوياً | D47: افتراض
A48: تأمين المعدات المملوكة | B48: 0.015 | C48: % من التكلفة سنوياً | D48: افتراض يحتاج تأكيداً بعرض شركة التأمين
A49: مصاريف إدارية وعمومية (تدقيق، قرطاسية، رسوم، بنوك) | B49: 4800 | C49: ر.ع / سنة | D49: افتراض (الدراسة الأصلية: صفر)
A50: المنافع العامة (كهرباء، ماء، اتصالات) | B50: 1800 | C50: ر.ع / سنة | D50: افتراض (الدراسة الأصلية: صفر)
A51: الفحص المخبري وأخذ العينات والتسويق | B51: 2400 | C51: ر.ع / سنة | D51: افتراض (الدراسة الأصلية: صفر)
A52: إعادة تأهيل الموقع (تدريجي) | B52: 2500 | C52: ر.ع / سنة | D52: افتراض — التزام قانوني بموجب قانون الثروة المعدنية والتصريح البيئي
A53: تجديد التراخيص والرسوم الحكومية | B53: 1600 | C53: ر.ع / سنة | D53: افتراض: تصريح بيئي 400 + ترخيص بلدي 100 + ما يعادل تجديد ترخيص التعدين (5,500 ÷ 5 سنوات)
A54: سابعاً: التمويل والتقييم
A55: مبلغ القرض البنكي | B55: 150000 | C55: ر.ع | D55: افتراض يحتاج تأكيداً — ضع صفراً إذا كان التمويل ذاتياً بالكامل
A56: معدل الفائدة السنوي | B56: 0.06 | C56: % سنوياً | D56: افتراض يحتاج تأكيداً من الجهة الممولة
A57: مدة سداد القرض (أقساط سنوية متساوية) | B57: 5 | C57: سنة | D57: افتراض (من 1 إلى 5 سنوات ضمن مدة الدراسة)
A58: رأس المال العامل — عدد أشهر التغطية | B58: 3 | C58: شهر | D58: افتراض: تغطية التكاليف النقدية حتى تحصيل قيمة أولى الشحنات
A59: معدل الخصم | B59: 0.12 | C59: % سنوياً | D59: افتراض: يعكس مخاطر التعدين الصغير وتقلب أسعار الكروم
A61: ثامناً: معطيات التشغيل الفعلية (من المالك — أكتوبر 2026)
A62: الإنتاج الصافي المستهدف (خام قابل للبيع) | B62: 60000 | C62: طن / سنة | D62: معطى من المالك — محجر كروم جبلي مع تتبع العروق بالحفر والقطع إلى باطن الأرض
A63: عدد الحفارات المستأجرة | B63: 5 | C63: حفار | D63: معطى من المالك
A64: أجرة الحفار بالساعة (شاملة المعدة والمشغل والديزل) | B64: 12 | C64: ر.ع / ساعة | D64: معطى من المالك

Sheet التراخيص
A1: التراخيص اللازمة لمزاولة النشاط والإطار التنظيمي
A2: الرسوم من الدراسة الأصلية — تُراجع مع جدول الرسوم الساري لدى وزارة الطاقة والمعادن وهيئة البيئة قبل التقديم
A4: م | B4: الترخيص | C4: الجهة المانحة | D4: الرسوم (ر.ع) | E4: المرحلة | F4: متطلبات الحصول على الترخيص
A5: 1 | B5: ترخيص التنقيب | C5: وزارة الطاقة والمعادن | D5: 2000 | E5: الاستكشاف (منجز) | F5: موافقة الجهات المختصة على الموقع المحدد: هيئة البيئة، وزارة الإسكان والتخطيط العمراني، وزارة التراث والسياحة، شرطة عُمان السلطانية، وزارة الدفاع، وزارة الثروة الزراعية والسمكية وموارد المياه، وزارة الداخلية
A6: 2 | B6: التصريح البيئي للتنقيب | C6: هيئة البيئة | D6: 400 | E6: الاستكشاف (منجز) | F6: موافقة وزارة الطاقة والمعادن، ودراسة بيئية تثبت عدم وجود تأثيرات بيئية في الموقع
A7: 3 | B7: ترخيص التعدين | C7: وزارة الطاقة والمعادن | D7: 5500 | E7: قبل الإنتاج | F7: تقرير تنقيبي شامل (الحفر والعينات)، تقدير الاحتياطي، دراسة الجدوى وخطة التعدين، الضمان المالي
A8: 4 | B8: التصريح البيئي للتعدين | C8: هيئة البيئة | D8: 400 | E8: قبل الإنتاج | F8: صدور الموافقة على ترخيص التعدين، ودراسة الأثر البيئي وخطة إعادة التأهيل
A9: 5 | B9: الترخيص البلدي | C9: بلدية شمال الشرقية | D9: 100 | E9: قبل الإنتاج | F9: السجل التجاري وعقود إيجار المواقع
A10: إجمالي تكلفة إصدار التراخيص | D10: =SUM(D5:D9) -> 8400
A12: الإطار التنظيمي الذي بُنيت عليه الدراسة
A13: م | B13: الموضوع | C13: المرجع | D13: الحكم وأثره في الدراسة
A14: 1 | B14: الإتاوة | C14: قانون الثروة المعدنية (م.س 19/2019) | F14: لا تقل عن 5% من إجمالي الإنتاج السنوي للخام المستغل. اعتُمدت 5% في الدراسة، وتُؤكَّد النسبة المحددة في ترخيص المشروع.
A15: 2 | B15: مساهمة تنمية المجتمع المحلي | C15: قانون الثروة المعدنية | F15: لا تقل عن 1% من الإنتاج السنوي تُدفع للجهة التي يحددها مجلس الوزراء. اعتُمدت 1%.
A16: 3 | B16: الضمان المالي والإيجار السنوي | C16: قانون الثروة المعدنية | F16: ضمان مالي لا يقل عن 1% من تكلفة المشروع قبل إصدار الترخيص، وإيجار سنوي للمساحة المرخصة. الدراسة تعتمد ضمانات بقيمة 55,000 ر.ع كما في الملف الأصلي.
A17: 4 | B17: تصدير خام الكروم | C17: قرار وزارة الطاقة والمعادن 18/2025 | F17: الحق الحصري في التصدير لشركة متاجرة المعادن (تابعة لشركة تنمية معادن عُمان)؛ لا يُصدَّر الخام بتركيز أقل من 36% ما لم يكن معالجاً وبموافقة كتابية من الوزارة؛ وللسوق المحلي حق الأولوية في الشراء. نافذ منذ منتصف 2026.
A18: 5 | B18: ضريبة الدخل | C18: قانون ضريبة الدخل | F18: 15% على الربح الخاضع للضريبة. النسبة المخفضة 3% للمؤسسات الصغيرة لا تشمل أنشطة استخراج الثروات الطبيعية.
A19: 6 | B19: ضريبة القيمة المضافة | C19: قانون ضريبة القيمة المضافة | F19: 5% على المبيعات المحلية والصادرات بنسبة صفر. تُحصَّل من المشتري وتُسترد على المشتريات، لذلك لم تُدرج ضمن التكاليف.
A20: 7 | B20: مأذونيات العمل | C20: قرار وزارة العمل 602/2025 | F20: صلاحية 24 شهراً؛ الرسوم 301 / 251 / 201 ر.ع حسب فئة المهنة؛ تخفيض 30% عند الالتزام بنسب التعمين ومضاعفتها عند عدم الالتزام.
A21: 8 | B21: الحماية الاجتماعية | C21: قانون الحماية الاجتماعية (م.س 52/2023) | F21: اشتراك صاحب العمل عن العُماني 14.5% من الأجر، واشتراكات الأمومة وإصابات العمل والإجازات المرضية عن الوافد، ونظام ادخار للوافدين 9% من يوليو 2027.

Sheet السوق والسعر
A1: تحليل السوق وبناء سعر البيع
A2: السعر المعتمد يُحتسب بطريقة صافي العائد (Netback) من السعر المرجعي العالمي نزولاً إلى موقع التجميع
A4: البند | B4: القيمة | C4: الوحدة | D4: المصدر / ملاحظات
A5: أولاً: سوق خام الكروم في سلطنة عُمان
A6: إنتاج السلطنة من خام الكروم (2025) | B6: 353538 | C6: طن | D6: وزارة الطاقة والمعادن — منشور في Times of Oman
A7: مبيعات خام الكروم (2025) | B7: 387995 | C7: طن | D7: المصدر نفسه
A8: قيمة المبيعات (2025) | B8: 15000000 | C8: ر.ع | D8: «تجاوزت 15 مليون ر.ع» — المصدر نفسه
A9: متوسط السعر المحقق وطنياً (2025) | B9: =B8/B7 -> 38.660292 | C9: ر.ع / طن | D9: محتسب: يشمل جميع الدرجات والمبيعات المحلية والتصدير — رقم مرجعي للتحقق من واقعية سعر الدراسة
A10: عدد المحاجر العاملة | B10: 29 | C10: محجر | D10: من ولاية شناص إلى ولاية وادي بني خالد
A11: متوسط إنتاج المحجر الواحد | B11: =B6/B10 -> 12190.966 | C11: طن / سنة | D11: محتسب — يُقارن بالطاقة الإنتاجية للمشروع
A12: الإنتاج المستهدف للسلطنة بحلول 2030 | B12: 400000 | C12: طن / سنة | D12: شركة تنمية معادن عُمان — Oman Observer
A13: الحد الأدنى لدرجة تصدير الخام غير المعالج | B13: 0.36 | C13: Cr2O3 | D13: القرار الوزاري 18/2025 — التصدير حصري عبر شركة متاجرة المعادن، وللسوق المحلي حق الأولوية
A14: ثانياً: الأسعار المرجعية العالمية — CIF الصين (SMM، 30 سبتمبر 2026)
A15: كروم عُماني كتل 30–32% | B15: 205 | C15: دولار / طن | D15: النطاق 200–210 (وكان 192.5 في 17 يونيو 2026)
A16: كروم جنوب أفريقيا كتل 38% | B16: 257.5 | C16: دولار / طن | D16: النطاق 255–260
A17: مركزات جنوب أفريقيا 40–42% | B17: 267.5 | C17: دولار / طن | D17: النطاق 265–270
A18: كروم تركي كتل 40–42% | B18: 340 | C18: دولار / طن | D18: النطاق 335–345 — يوضح علاوة الدرجات العالية والكتل الصلبة
A19: ثالثاً: بناء سعر البيع المعتمد (صافي العائد عند موقع التجميع)
A20: السعر المرجعي CIF الصين للخام 30–32% | B20: =CifBench -> 200 | C20: دولار / طن | D20: من ورقة الافتراضات
A21: سعر وحدة الكروم (لكل 1% Cr2O3) | B21: =B20/(BenchGrade*100) -> 6.4516129 | C21: دولار / وحدة | D21: السعر المرجعي ÷ درجة الخام المرجعي
A22: درجة خام المشروع | B22: =OreGrade -> 0.32 | C22: Cr2O3 | D22: من ورقة الافتراضات
A23: السعر المعادل CIF لخام المشروع | B23: =B21*B22*100 -> 206.45161 | C23: دولار / طن
A24: السعر المعادل CIF لخام المشروع | B24: =B23*FxRate -> 79.380645 | C24: ر.ع / طن
A25: (-) الشحن البحري | B25: =SeaFreight*FxRate -> 9.228 | C25: ر.ع / طن
A26: (-) المناولة والتخزين والتحميل في الميناء | B26: =PortCost -> 2.5 | C26: ر.ع / طن
A27: (-) هامش التسويق والفحص والتمويل | B27: =B24*TraderM -> 7.9380645 | C27: ر.ع / طن
A28: صافي السعر تسليم الميناء | B28: =B24-B25-B26-B27 -> 59.714581 | C28: ر.ع / طن
A29: (-) النقل البري من موقع التجميع إلى الميناء | B29: =HaulDist*TruckRate -> 6 | C29: ر.ع / طن
A30: صافي العائد عند موقع التجميع | B30: =B28-B29 -> 53.714581 | C30: ر.ع / طن
A31: (-) الخصم التحوّطي | B31: =B30*PriceDisc -> 6.4457497 | C31: ر.ع / طن
A32: صافي سعر التصدير عند موقع التجميع | B32: =B30-B31 -> 47.268831 | C32: ر.ع / طن | D32: يُستخدم لحصة التصدير فقط — انظر «خامساً» أدناه
A33: رابعاً: التحقق
A34: نسبة سعر الدراسة إلى المتوسط الوطني المحقق 2025 | B34: =SalePrice/NatAvgPrice -> 0.99999245 | C34: مرة | D34: =IF(ABS(B34-1)<0.005,"السعر المعتمد يساوي المتوسط الوطني المحقق 2025.",IF(B34>1,"السعر المعتمد أعلى من المتوسط الوطني المحقق 2025 — يُبرَّر بعقد أو عرض شراء.","السعر المعتمد أقل من المتوسط الوطني المحقق 2025 (تحفّظ).")) -> السعر المعتمد يساوي المتوسط الوطني المحقق 2025.
A35: هل تحقق درجة الخام شرط تصدير الخام غير المعالج؟ | B35: =IF(OreGrade>=MinExportGrade,"نعم","لا") -> لا | C35: — | D35: =IF(OreGrade>=MinExportGrade,"الدرجة مطابقة لشرط التصدير (36% فأكثر).","تنبيه: الدرجة أقل من 36% — لا يُسمح بتصدير الخام غير المعالج. يُباع محلياً (مصانع المعالجة/الفيروكروم) أو يُعالَج ويُصدَّر عبر شركة متاجرة المعادن بموافقة الوزارة، وقد ينخفض السعر المحقق عن المحتسب أعلاه.") -> تنبيه: الدرجة أقل من 36% — لا يُسمح بتصدير الخام غير المعالج. يُباع محلياً (مصانع المعالجة/الفيروكروم) أو يُعالَج ويُصدَّر عبر شركة متاجرة المعادن بموافقة الوزارة، وقد ينخفض السعر المحقق عن المحتسب أعلاه.
A37: خامساً: مسار البيع — بيع محلي و/أو تصدير
A38: سعر البيع المحلي عند موقع التجميع | B38: 38.66 | C38: ر.ع / طن | D38: افتراض يحتاج تأكيداً = متوسط السعر الوطني المحقق 2025 (B9). يُستبدل بعرض مشترٍ محلي (مصانع المعالجة / الفيروكروم) تسليم موقع التجميع
A39: نسبة المبيعات المحلية من الكمية المباعة | B39: 1 | C39: % | D39: 100% = بيع محلي بالكامل (الحالة الأساسية لأن درجة الخام أقل من 36%). الباقي يُصدَّر عبر شركة متاجرة المعادن بصافي سعر التصدير
A40: صافي سعر التصدير عند موقع التجميع | B40: =B32 -> 47.268831 | C40: ر.ع / طن | D40: من «ثالثاً» أعلاه
A41: سعر البيع المعتمد في الدراسة (متوسط مرجّح) | B41: =B38*B39+B40*(1-B39) -> 38.66 | C41: ر.ع / طن | D41: يُستخدم في الإيرادات وجميع المؤشرات والحساسية
A42: التحقق من شرط درجة التصدير | B42: =IF(OR(B39>=1,OreGrade>=MinExportGrade),"مطابق","مخالف") -> مطابق | C42: — | D42: =IF(B39>=1,"البيع محلي بالكامل — لا ينطبق شرط درجة التصدير.",IF(OreGrade>=MinExportGrade,"الدرجة تسمح بتصدير الخام غير المعالج عبر شركة متاجرة المعادن.","تنبيه: جزء من المبيعات مفترض للتصدير والدرجة أقل من 36% — يلزم معالجة الخام وموافقة الوزارة، أو رفع نسبة البيع المحلي إلى 100%.")) -> البيع محلي بالكامل — لا ينطبق شرط درجة التصدير.

Sheet الخطة الفنية والإنتاج
A1: الخطة الفنية وبرنامج الإنتاج
A2: محجر كروم جبلي — تتبع العروق بالحفر والقطع إلى باطن الأرض بحفارات مستأجرة بالساعة — فرز يدوي — بيع من موقع التجميع
A4: البند | B4: الوحدة | C4: القيمة | D4: ملاحظات
A5: عدد الحفارات المستأجرة (شاملة المشغل والديزل) | B5: عدد | C5: =ExcavNo -> 5 | D5: من «الافتراضات» — معطى من المالك
A6: ساعات العمل المجدولة للمعدة في السنة | B6: ساعة | C6: =WorkDays*ShiftHrs -> 3120 | D6: أيام العمل × ساعات العمل اليومية (312 × 10)
A7: ساعات التشغيل الفعلية للمعدة | B7: ساعة | C7: =C6*AvailFactor -> 2340 | D7: بعد معامل الجاهزية — تُستخدم لوقود المعدات المملوكة وللتحقق من الطاقة
A8: الخام القابل للبيع المستهدف (الطاقة الإنتاجية) | B8: طن | C8: =TargetProd -> 60000 | D8: معطى من المالك: 60,000 طن صافٍ سنوياً
A9: الخام الخارج من المحجر المطلوب (ROM) | B9: طن | C9: =SaleCap/SortRecov -> 70588.235 | D9: الصافي ÷ نسبة الاسترداد بعد الفرز
A10: إجمالي الصخور المطلوب تحريكها (خام + عقيم) | B10: طن | C10: =ROMCap*(1+StripRatio) -> 352941.18 | D10: ROM × (1 + نسبة التعرية)
A11: الصخور العقيمة | B11: طن | C11: =RockCap-ROMCap -> 282352.94
A12: طاقة الحفارات على التكسير والتحميل | B12: طن | C12: =C5*BrkProd*C7 -> 409500 | D12: عدد الحفارات × الإنتاجية × ساعات التشغيل الفعلية
A13: الصخور المطلوبة إلى طاقة الحفارات | B13: % | C13: =IF(C12>0,C10/C12,0) -> 0.86188321 | D13: أكثر من 100% = الحفارات لا تكفي عند نسبة التعرية المفترضة
A14: التحقق من كفاية الحفارات | C14: =IF(C13<=1,"كافية — المطلوب "&TEXT(C13,"0%")&" من طاقة الحفارات","غير كافية — المطلوب "&TEXT(C13,"0%")&" من طاقتها؛ يلزم ألا تزيد نسبة التعرية عن "&TEXT(C15,"0.0")&" أو إنتاجية أعلى أو حفارات إضافية") -> كافية — المطلوب 86% من طاقة الحفارات
A15: أقصى نسبة تعرية تسمح بها طاقة الحفارات | B15: طن / طن | C15: =IF(ROMCap>0,C12/ROMCap-1,0) -> 4.80125 | D15: للمقارنة بنسبة التعرية في «الافتراضات»
A16: للمقارنة: متوسط إنتاج المحجر الواحد في السلطنة (2025) | B16: طن | C16: =NatAvgOutput -> 12190.966 | D16: 353,538 طن ÷ 29 محجراً — من ورقة «السوق والسعر»
A17: عمر الاحتياطي المفترض عند الطاقة الكاملة | B17: سنة | C17: =IF(ROMCap>0,OreReserve/ROMCap,0) -> 5.6666667 | D17: الاحتياطي ÷ الخام المستخرج سنوياً
A19: برنامج الإنتاج السنوي | B19: الوحدة | C19: 0 | D19: 1 | E19: 2 | F19: 3 | G19: 4 | H19: 5 | I19: الإجمالي
A20: نسبة استغلال الطاقة الإنتاجية | B20: % | D20: 1 | E20: 1 | F20: 1 | G20: 1 | H20: 1
A21: نسبة الأعباء الإضافية لتتبع العروق إلى باطن الأرض | B21: % | D21: 0 | E21: 0.1 | F21: 0.2 | G21: 0.3 | H21: 0.4
A22: إجمالي الصخور المحفورة | B22: طن | D22: =RockCap*D20 -> 352941.18 | E22: =RockCap*E20 -> 352941.18 | F22: =RockCap*F20 -> 352941.18 | G22: =RockCap*G20 -> 352941.18 | H22: =RockCap*H20 -> 352941.18 | I22: =SUM(D22:H22) -> 1764705.9
A23: الخام الخارج من المحجر (ROM) | B23: طن | D23: =ROMCap*D20 -> 70588.235 | E23: =ROMCap*E20 -> 70588.235 | F23: =ROMCap*F20 -> 70588.235 | G23: =ROMCap*G20 -> 70588.235 | H23: =ROMCap*H20 -> 70588.235 | I23: =SUM(D23:H23) -> 352941.18
A24: الخام القابل للبيع | B24: طن | D24: =D23*SortRecov*F_Vol -> 60000 | E24: =E23*SortRecov*F_Vol -> 60000 | F24: =F23*SortRecov*F_Vol -> 60000 | G24: =G23*SortRecov*F_Vol -> 60000 | H24: =H23*SortRecov*F_Vol -> 60000 | I24: =SUM(D24:H24) -> 300000
A25: ساعات إيجار الحفارات (شاملة أعباء تتبع العروق) | B25: ساعة | D25: =ExcavNo*SchedHrs*D20*(1+D21) -> 15600 | E25: =ExcavNo*SchedHrs*E20*(1+E21) -> 17160 | F25: =ExcavNo*SchedHrs*F20*(1+F21) -> 18720 | G25: =ExcavNo*SchedHrs*G20*(1+G21) -> 20280 | H25: =ExcavNo*SchedHrs*H20*(1+H21) -> 21840 | I25: =SUM(D25:H25) -> 93600
A26: الاستنزاف التراكمي للاحتياطي | B26: طن | D26: =SUM($D$23:D23) -> 70588.235 | E26: =SUM($D$23:E23) -> 141176.47 | F26: =SUM($D$23:F23) -> 211764.71 | G26: =SUM($D$23:G23) -> 282352.94 | H26: =SUM($D$23:H23) -> 352941.18
A27: الاحتياطي المتبقي آخر السنة | B27: طن | C27: =OreReserve -> 400000 | D27: =OreReserve-D26 -> 329411.76 | E27: =OreReserve-E26 -> 258823.53 | F27: =OreReserve-F26 -> 188235.29 | G27: =OreReserve-G26 -> 117647.06 | H27: =OreReserve-H26 -> 47058.824
A28: كفاية الاحتياطي لمدة الدراسة | B28: =IF($H$27>=0,"الاحتياطي المفترض كافٍ لخمس سنوات تشغيل","تنبيه: الاحتياطي المفترض ("&TEXT(OreReserve,"#,##0")&" طن) لا يكفي — المطلوب "&TEXT($H$26,"#,##0")&" طن خام لخمس سنوات") -> الاحتياطي المفترض كافٍ لخمس سنوات تشغيل
A29: نسبة الأعباء الإضافية تمثل الزيادة في ساعات الحفر والقطع والتحميل مع تعمّق العروق (ممرات أضيق، مسافات نقل أطول، تدعيم وتصريف مياه). تُطبَّق على إيجار الحفارات والمواد المستهلكة المتغيرة — قيم تقديرية قابلة للتعديل.
A31: أسلوب التعدين وتسلسل العمليات
A32: 1) محجر جبلي مكشوف في المرحلة الأولى، ثم تتبع عروق الكروم بالحفر والقطع إلى باطن الأرض ابتداءً من السنة الثانية.
A33: 2) التكسير والقطع والتحميل بخمسة حفارات مستأجرة بالساعة (12 ر.ع/ساعة شاملة المعدة والمشغل والديزل)، 10 ساعات يومياً و6 أيام أسبوعياً.
A34: 3) نقل الخام بقلاب مملوك إلى ساحة الفرز، والتجميع والتحميل بشيول مملوك؛ العقيم يُزاح ويُرصّ في المرمى بالحفارات.
A35: 4) فرز وتنقية الخام يدوياً لرفع الدرجة، ثم أخذ العينات وتحليلها والبيع من موقع التجميع.
A36: 5) إعادة تأهيل تدريجية وفق التصريح البيئي وخطة الإغلاق.
A37: ملاحظة: الأعمال تحت السطح قد تتطلب اشتراطات سلامة وموافقات إضافية من وزارة الطاقة والمعادن — تُؤكَّد قبل التنفيذ. الدراسة لا تتضمن تفجيراً.

Sheet الإنتاج الشهري
A1: برنامج الإنتاج الشهري
A2: يوزّع الإنتاج السنوي من «الخطة الفنية والإنتاج» على الأشهر بحسب أيام العمل في كل شهر. السنة الأولى تبدأ من شهر بدء الإنتاج في «الجدول الزمني». الخلايا الصفراء فقط قابلة للتعديل.
A4: أولاً: الإنتاج الشهري — 5 سنوات تشغيل (60 شهراً) | M4: ثانياً: أيام العمل في كل شهر
A5: الشهر | B5: سنة التشغيل | C5: رقم الشهر | D5: أيام العمل | E5: نسبة استغلال الطاقة | F5: إجمالي الصخور المحفورة (طن) | G5: الخام الخارج من المحجر ROM (طن) | H5: الخام القابل للبيع (طن) | I5: متوسط الإنتاج اليومي القابل للبيع (طن/يوم) | J5: الخام القابل للبيع — تراكمي (طن) | K5: الاحتياطي المتبقي آخر الشهر (طن) | M5: الشهر | N5: أيام العمل
A6: =EDATE($N$21,C6-1) -> 46661 | B6: =INT((C6-1)/12)+1 -> 1 | C6: 1 | D6: =INDEX($N$6:$N$17,MONTH(A6)) -> 26 | E6: =INDEX('الخطة الفنية والإنتاج'!$D$20:$H$20,B6) -> 1 | F6: =IF($N$18>0,INDEX('الخطة الفنية والإنتاج'!$D$22:$H$22,B6)*D6/$N$18,0) -> 29411.765 | G6: =IF($N$18>0,INDEX('الخطة الفنية والإنتاج'!$D$23:$H$23,B6)*D6/$N$18,0) -> 5882.3529 | H6: =IF($N$18>0,INDEX('الخطة الفنية والإنتاج'!$D$24:$H$24,B6)*D6/$N$18,0) -> 5000 | I6: =IF(D6>0,H6/D6,0) -> 192.30769 | J6: =SUM($H$6:H6) -> 5000 | K6: =OreReserve-SUM($G$6:G6) -> 394117.65 | M6: يناير | N6: 26
A7: =EDATE($N$21,C7-1) -> 46692 | B7: =INT((C7-1)/12)+1 -> 1 | C7: 2 | D7: =INDEX($N$6:$N$17,MONTH(A7)) -> 26 | E7: =INDEX('الخطة الفنية والإنتاج'!$D$20:$H$20,B7) -> 1 | F7: =IF($N$18>0,INDEX('الخطة الفنية والإنتاج'!$D$22:$H$22,B7)*D7/$N$18,0) -> 29411.765 | G7: =IF($N$18>0,INDEX('الخطة الفنية والإنتاج'!$D$23:$H$23,B7)*D7/$N$18,0) -> 5882.3529 | H7: =IF($N$18>0,INDEX('الخطة الفنية والإنتاج'!$D$24:$H$24,B7)*D7/$N$18,0) -> 5000 | I7: =IF(D7>0,H7/D7,0) -> 192.30769 | J7: =SUM($H$6:H7) -> 10000 | K7: =OreReserve-SUM($G$6:G7) -> 388235.29 | M7: فبراير | N7: 26
A8: =EDATE($N$21,C8-1) -> 46722 | B8: =INT((C8-1)/12)+1 -> 1 | C8: 3 | D8: =INDEX($N$6:$N$17,MONTH(A8)) -> 26 | E8: =INDEX('الخطة الفنية والإنتاج'!$D$20:$H$20,B8) -> 1 | F8: =IF($N$18>0,INDEX('الخطة الفنية والإنتاج'!$D$22:$H$22,B8)*D8/$N$18,0) -> 29411.765 | G8: =IF($N$18>0,INDEX('الخطة الفنية والإنتاج'!$D$23:$H$23,B8)*D8/$N$18,0) -> 5882.3529 | H8: =IF($N$18>0,INDEX('الخطة الفنية والإنتاج'!$D$24:$H$24,B8)*D8/$N$18,0) -> 5000 | I8: =IF(D8>0,H8/D8,0) -> 192.30769 | J8: =SUM($H$6:H8) -> 15000 | K8: =OreReserve-SUM($G$6:G8) -> 382352.94 | M8: مارس | N8: 26
A9: =EDATE($N$21,C9-1) -> 46753 | B9: =INT((C9-1)/12)+1 -> 1 | C9: 4 | D9: =INDEX($N$6:$N$17,MONTH(A9)) -> 26 | E9: =INDEX('الخطة الفنية والإنتاج'!$D$20:$H$20,B9) -> 1 | F9: =IF($N$18>0,INDEX('الخطة الفنية والإنتاج'!$D$22:$H$22,B9)*D9/$N$18,0) -> 29411.765 | G9: =IF($N$18>0,INDEX('الخطة الفنية والإنتاج'!$D$23:$H$23,B9)*D9/$N$18,0) -> 5882.3529 | H9: =IF($N$18>0,INDEX('الخطة الفنية والإنتاج'!$D$24:$H$24,B9)*D9/$N$18,0) -> 5000 | I9: =IF(D9>0,H9/D9,0) -> 192.30769 | J9: =SUM($H$6:H9) -> 20000 | K9: =OreReserve-SUM($G$6:G9) -> 376470.59 | M9: أبريل | N9: 26
A10: =EDATE($N$21,C10-1) -> 46784 | B10: =INT((C10-1)/12)+1 -> 1 | C10: 5 | D10: =INDEX($N$6:$N$17,MONTH(A10)) -> 26 | E10: =INDEX('الخطة الفنية والإنتاج'!$D$20:$H$20,B10) -> 1 | F10: =IF($N$18>0,INDEX('الخطة الفنية والإنتاج'!$D$22:$H$22,B10)*D10/$N$18,0) -> 29411.765 | G10: =IF($N$18>0,INDEX('الخطة الفنية والإنتاج'!$D$23:$H$23,B10)*D10/$N$18,0) -> 5882.3529 | H10: =IF($N$18>0,INDEX('الخطة الفنية والإنتاج'!$D$24:$H$24,B10)*D10/$N$18,0) -> 5000 | I10: =IF(D10>0,H10/D10,0) -> 192.30769 | J10: =SUM($H$6:H10) -> 25000 | K10: =OreReserve-SUM($G$6:G10) -> 370588.24 | M10: مايو | N10: 26
A11: =EDATE($N$21,C11-1) -> 46813 | B11: =INT((C11-1)/12)+1 -> 1 | C11: 6 | D11: =INDEX($N$6:$N$17,MONTH(A11)) -> 26 | E11: =INDEX('الخطة الفنية والإنتاج'!$D$20:$H$20,B11) -> 1 | F11: =IF($N$18>0,INDEX('الخطة الفنية والإنتاج'!$D$22:$H$22,B11)*D11/$N$18,0) -> 29411.765 | G11: =IF($N$18>0,INDEX('الخطة الفنية والإنتاج'!$D$23:$H$23,B11)*D11/$N$18,0) -> 5882.3529 | H11: =IF($N$18>0,INDEX('الخطة الفنية والإنتاج'!$D$24:$H$24,B11)*D11/$N$18,0) -> 5000 | I11: =IF(D11>0,H11/D11,0) -> 192.30769 | J11: =SUM($H$6:H11) -> 30000 | K11: =OreReserve-SUM($G$6:G11) -> 364705.88 | M11: يونيو | N11: 26
A12: =EDATE($N$21,C12-1) -> 46844 | B12: =INT((C12-1)/12)+1 -> 1 | C12: 7 | D12: =INDEX($N$6:$N$17,MONTH(A12)) -> 26 | E12: =INDEX('الخطة الفنية والإنتاج'!$D$20:$H$20,B12) -> 1 | F12: =IF($N$18>0,INDEX('الخطة الفنية والإنتاج'!$D$22:$H$22,B12)*D12/$N$18,0) -> 29411.765 | G12: =IF($N$18>0,INDEX('الخطة الفنية والإنتاج'!$D$23:$H$23,B12)*D12/$N$18,0) -> 5882.3529 | H12: =IF($N$18>0,INDEX('الخطة الفنية والإنتاج'!$D$24:$H$24,B12)*D12/$N$18,0) -> 5000 | I12: =IF(D12>0,H12/D12,0) -> 192.30769 | J12: =SUM($H$6:H12) -> 35000 | K12: =OreReserve-SUM($G$6:G12) -> 358823.53 | M12: يوليو | N12: 26
A13: =EDATE($N$21,C13-1) -> 46874 | B13: =INT((C13-1)/12)+1 -> 1 | C13: 8 | D13: =INDEX($N$6:$N$17,MONTH(A13)) -> 26 | E13: =INDEX('الخطة الفنية والإنتاج'!$D$20:$H$20,B13) -> 1 | F13: =IF($N$18>0,INDEX('الخطة الفنية والإنتاج'!$D$22:$H$22,B13)*D13/$N$18,0) -> 29411.765 | G13: =IF($N$18>0,INDEX('الخطة الفنية والإنتاج'!$D$23:$H$23,B13)*D13/$N$18,0) -> 5882.3529 | H13: =IF($N$18>0,INDEX('الخطة الفنية والإنتاج'!$D$24:$H$24,B13)*D13/$N$18,0) -> 5000 | I13: =IF(D13>0,H13/D13,0) -> 192.30769 | J13: =SUM($H$6:H13) -> 40000 | K13: =OreReserve-SUM($G$6:G13) -> 352941.18 | M13: أغسطس | N13: 26
A14: =EDATE($N$21,C14-1) -> 46905 | B14: =INT((C14-1)/12)+1 -> 1 | C14: 9 | D14: =INDEX($N$6:$N$17,MONTH(A14)) -> 26 | E14: =INDEX('الخطة الفنية والإنتاج'!$D$20:$H$20,B14) -> 1 | F14: =IF($N$18>0,INDEX('الخطة الفنية والإنتاج'!$D$22:$H$22,B14)*D14/$N$18,0) -> 29411.765 | G14: =IF($N$18>0,INDEX('الخطة الفنية والإنتاج'!$D$23:$H$23,B14)*D14/$N$18,0) -> 5882.3529 | H14: =IF($N$18>0,INDEX('الخطة الفنية والإنتاج'!$D$24:$H$24,B14)*D14/$N$18,0) -> 5000 | I14: =IF(D14>0,H14/D14,0) -> 192.30769 | J14: =SUM($H$6:H14) -> 45000 | K14: =OreReserve-SUM($G$6:G14) -> 347058.82 | M14: سبتمبر | N14: 26
A15: =EDATE($N$21,C15-1) -> 46935 | B15: =INT((C15-1)/12)+1 -> 1 | C15: 10 | D15: =INDEX($N$6:$N$17,MONTH(A15)) -> 26 | E15: =INDEX('الخطة الفنية والإنتاج'!$D$20:$H$20,B15) -> 1 | F15: =IF($N$18>0,INDEX('الخطة الفنية والإنتاج'!$D$22:$H$22,B15)*D15/$N$18,0) -> 29411.765 | G15: =IF($N$18>0,INDEX('الخطة الفنية والإنتاج'!$D$23:$H$23,B15)*D15/$N$18,0) -> 5882.3529 | H15: =IF($N$18>0,INDEX('الخطة الفنية والإنتاج'!$D$24:$H$24,B15)*D15/$N$18,0) -> 5000 | I15: =IF(D15>0,H15/D15,0) -> 192.30769 | J15: =SUM($H$6:H15) -> 50000 | K15: =OreReserve-SUM($G$6:G15) -> 341176.47 | M15: أكتوبر | N15: 26
A16: =EDATE($N$21,C16-1) -> 46966 | B16: =INT((C16-1)/12)+1 -> 1 | C16: 11 | D16: =INDEX($N$6:$N$17,MONTH(A16)) -> 26 | E16: =INDEX('الخطة الفنية والإنتاج'!$D$20:$H$20,B16) -> 1 | F16: =IF($N$18>0,INDEX('الخطة الفنية والإنتاج'!$D$22:$H$22,B16)*D16/$N$18,0) -> 29411.765 | G16: =IF($N$18>0,INDEX('الخطة الفنية والإنتاج'!$D$23:$H$23,B16)*D16/$N$18,0) -> 5882.3529 | H16: =IF($N$18>0,INDEX('الخطة الفنية والإنتاج'!$D$24:$H$24,B16)*D16/$N$18,0) -> 5000 | I16: =IF(D16>0,H16/D16,0) -> 192.30769 | J16: =SUM($H$6:H16) -> 55000 | K16: =OreReserve-SUM($G$6:G16) -> 335294.12 | M16: نوفمبر | N16: 26
A17: =EDATE($N$21,C17-1) -> 46997 | B17: =INT((C17-1)/12)+1 -> 1 | C17: 12 | D17: =INDEX($N$6:$N$17,MONTH(A17)) -> 26 | E17: =INDEX('الخطة الفنية والإنتاج'!$D$20:$H$20,B17) -> 1 | F17: =IF($N$18>0,INDEX('الخطة الفنية والإنتاج'!$D$22:$H$22,B17)*D17/$N$18,0) -> 29411.765 | G17: =IF($N$18>0,INDEX('الخطة الفنية والإنتاج'!$D$23:$H$23,B17)*D17/$N$18,0) -> 5882.3529 | H17: =IF($N$18>0,INDEX('الخطة الفنية والإنتاج'!$D$24:$H$24,B17)*D17/$N$18,0) -> 5000 | I17: =IF(D17>0,H17/D17,0) -> 192.30769 | J17: =SUM($H$6:H17) -> 60000 | K17: =OreReserve-SUM($G$6:G17) -> 329411.76 | M17: ديسمبر | N17: 26
A18: =EDATE($N$21,C18-1) -> 47027 | B18: =INT((C18-1)/12)+1 -> 2 | C18: 13 | D18: =INDEX($N$6:$N$17,MONTH(A18)) -> 26 | E18: =INDEX('الخطة الفنية والإنتاج'!$D$20:$H$20,B18) -> 1 | F18: =IF($N$18>0,INDEX('الخطة الفنية والإنتاج'!$D$22:$H$22,B18)*D18/$N$18,0) -> 29411.765 | G18: =IF($N$18>0,INDEX('الخطة الفنية والإنتاج'!$D$23:$H$23,B18)*D18/$N$18,0) -> 5882.3529 | H18: =IF($N$18>0,INDEX('الخطة الفنية والإنتاج'!$D$24:$H$24,B18)*D18/$N$18,0) -> 5000 | I18: =IF(D18>0,H18/D18,0) -> 192.30769 | J18: =SUM($H$6:H18) -> 65000 | K18: =OreReserve-SUM($G$6:G18) -> 323529.41 | M18: مجموع أيام العمل في السنة | N18: =SUM(N6:N17) -> 312
A19: =EDATE($N$21,C19-1) -> 47058 | B19: =INT((C19-1)/12)+1 -> 2 | C19: 14 | D19: =INDEX($N$6:$N$17,MONTH(A19)) -> 26 | E19: =INDEX('الخطة الفنية والإنتاج'!$D$20:$H$20,B19) -> 1 | F19: =IF($N$18>0,INDEX('الخطة الفنية والإنتاج'!$D$22:$H$22,B19)*D19/$N$18,0) -> 29411.765 | G19: =IF($N$18>0,INDEX('الخطة الفنية والإنتاج'!$D$23:$H$23,B19)*D19/$N$18,0) -> 5882.3529 | H19: =IF($N$18>0,INDEX('الخطة الفنية والإنتاج'!$D$24:$H$24,B19)*D19/$N$18,0) -> 5000 | I19: =IF(D19>0,H19/D19,0) -> 192.30769 | J19: =SUM($H$6:H19) -> 70000 | K19: =OreReserve-SUM($G$6:G19) -> 317647.06 | M19: أيام العمل في ورقة «الافتراضات» | N19: =WorkDays -> 312
A20: =EDATE($N$21,C20-1) -> 47088 | B20: =INT((C20-1)/12)+1 -> 2 | C20: 15 | D20: =INDEX($N$6:$N$17,MONTH(A20)) -> 26 | E20: =INDEX('الخطة الفنية والإنتاج'!$D$20:$H$20,B20) -> 1 | F20: =IF($N$18>0,INDEX('الخطة الفنية والإنتاج'!$D$22:$H$22,B20)*D20/$N$18,0) -> 29411.765 | G20: =IF($N$18>0,INDEX('الخطة الفنية والإنتاج'!$D$23:$H$23,B20)*D20/$N$18,0) -> 5882.3529 | H20: =IF($N$18>0,INDEX('الخطة الفنية والإنتاج'!$D$24:$H$24,B20)*D20/$N$18,0) -> 5000 | I20: =IF(D20>0,H20/D20,0) -> 192.30769 | J20: =SUM($H$6:H20) -> 75000 | K20: =OreReserve-SUM($G$6:G20) -> 311764.71 | M20: التحقق | N20: =IF(N18=N19,"مطابق","المجموع يختلف عن «الافتراضات» — الإنتاج السنوي محسوب على أيام الافتراضات") -> مطابق
A21: =EDATE($N$21,C21-1) -> 47119 | B21: =INT((C21-1)/12)+1 -> 2 | C21: 16 | D21: =INDEX($N$6:$N$17,MONTH(A21)) -> 26 | E21: =INDEX('الخطة الفنية والإنتاج'!$D$20:$H$20,B21) -> 1 | F21: =IF($N$18>0,INDEX('الخطة الفنية والإنتاج'!$D$22:$H$22,B21)*D21/$N$18,0) -> 29411.765 | G21: =IF($N$18>0,INDEX('الخطة الفنية والإنتاج'!$D$23:$H$23,B21)*D21/$N$18,0) -> 5882.3529 | H21: =IF($N$18>0,INDEX('الخطة الفنية والإنتاج'!$D$24:$H$24,B21)*D21/$N$18,0) -> 5000 | I21: =IF(D21>0,H21/D21,0) -> 192.30769 | J21: =SUM($H$6:H21) -> 80000 | K21: =OreReserve-SUM($G$6:G21) -> 305882.35 | M21: شهر بدء الإنتاج (من «الجدول الزمني») | N21: =EDATE(StartDate,'الجدول الزمني'!$C$28-1) -> 46661
A22: =EDATE($N$21,C22-1) -> 47150 | B22: =INT((C22-1)/12)+1 -> 2 | C22: 17 | D22: =INDEX($N$6:$N$17,MONTH(A22)) -> 26 | E22: =INDEX('الخطة الفنية والإنتاج'!$D$20:$H$20,B22) -> 1 | F22: =IF($N$18>0,INDEX('الخطة الفنية والإنتاج'!$D$22:$H$22,B22)*D22/$N$18,0) -> 29411.765 | G22: =IF($N$18>0,INDEX('الخطة الفنية والإنتاج'!$D$23:$H$23,B22)*D22/$N$18,0) -> 5882.3529 | H22: =IF($N$18>0,INDEX('الخطة الفنية والإنتاج'!$D$24:$H$24,B22)*D22/$N$18,0) -> 5000 | I22: =IF(D22>0,H22/D22,0) -> 192.30769 | J22: =SUM($H$6:H22) -> 85000 | K22: =OreReserve-SUM($G$6:G22) -> 300000 | M22: عدّل أيام كل شهر لمراعاة رمضان والأعياد وحر الصيف؛ يُعاد توزيع الإنتاج السنوي فقط دون تغيير مجموعه.
A23: =EDATE($N$21,C23-1) -> 47178 | B23: =INT((C23-1)/12)+1 -> 2 | C23: 18 | D23: =INDEX($N$6:$N$17,MONTH(A23)) -> 26 | E23: =INDEX('الخطة الفنية والإنتاج'!$D$20:$H$20,B23) -> 1 | F23: =IF($N$18>0,INDEX('الخطة الفنية والإنتاج'!$D$22:$H$22,B23)*D23/$N$18,0) -> 29411.765 | G23: =IF($N$18>0,INDEX('الخطة الفنية والإنتاج'!$D$23:$H$23,B23)*D23/$N$18,0) -> 5882.3529 | H23: =IF($N$18>0,INDEX('الخطة الفنية والإنتاج'!$D$24:$H$24,B23)*D23/$N$18,0) -> 5000 | I23: =IF(D23>0,H23/D23,0) -> 192.30769 | J23: =SUM($H$6:H23) -> 90000 | K23: =OreReserve-SUM($G$6:G23) -> 294117.65
A24: =EDATE($N$21,C24-1) -> 47209 | B24: =INT((C24-1)/12)+1 -> 2 | C24: 19 | D24: =INDEX($N$6:$N$17,MONTH(A24)) -> 26 | E24: =INDEX('الخطة الفنية والإنتاج'!$D$20:$H$20,B24) -> 1 | F24: =IF($N$18>0,INDEX('الخطة الفنية والإنتاج'!$D$22:$H$22,B24)*D24/$N$18,0) -> 29411.765 | G24: =IF($N$18>0,INDEX('الخطة الفنية والإنتاج'!$D$23:$H$23,B24)*D24/$N$18,0) -> 5882.3529 | H24: =IF($N$18>0,INDEX('الخطة الفنية والإنتاج'!$D$24:$H$24,B24)*D24/$N$18,0) -> 5000 | I24: =IF(D24>0,H24/D24,0) -> 192.30769 | J24: =SUM($H$6:H24) -> 95000 | K24: =OreReserve-SUM($G$6:G24) -> 288235.29 | M24: ثالثاً: مطابقة الخام القابل للبيع مع الورقة السنوية
A25: =EDATE($N$21,C25-1) -> 47239 | B25: =INT((C25-1)/12)+1 -> 2 | C25: 20 | D25: =INDEX($N$6:$N$17,MONTH(A25)) -> 26 | E25: =INDEX('الخطة الفنية والإنتاج'!$D$20:$H$20,B25) -> 1 | F25: =IF($N$18>0,INDEX('الخطة الفنية والإنتاج'!$D$22:$H$22,B25)*D25/$N$18,0) -> 29411.765 | G25: =IF($N$18>0,INDEX('الخطة الفنية والإنتاج'!$D$23:$H$23,B25)*D25/$N$18,0) -> 5882.3529 | H25: =IF($N$18>0,INDEX('الخطة الفنية والإنتاج'!$D$24:$H$24,B25)*D25/$N$18,0) -> 5000 | I25: =IF(D25>0,H25/D25,0) -> 192.30769 | J25: =SUM($H$6:H25) -> 100000 | K25: =OreReserve-SUM($G$6:G25) -> 282352.94 | M25: سنة التشغيل | N25: مجموع الأشهر (طن) | O25: الورقة السنوية (طن) | P25: الفرق (طن)
A26: =EDATE($N$21,C26-1) -> 47270 | B26: =INT((C26-1)/12)+1 -> 2 | C26: 21 | D26: =INDEX($N$6:$N$17,MONTH(A26)) -> 26 | E26: =INDEX('الخطة الفنية والإنتاج'!$D$20:$H$20,B26) -> 1 | F26: =IF($N$18>0,INDEX('الخطة الفنية والإنتاج'!$D$22:$H$22,B26)*D26/$N$18,0) -> 29411.765 | G26: =IF($N$18>0,INDEX('الخطة الفنية والإنتاج'!$D$23:$H$23,B26)*D26/$N$18,0) -> 5882.3529 | H26: =IF($N$18>0,INDEX('الخطة الفنية والإنتاج'!$D$24:$H$24,B26)*D26/$N$18,0) -> 5000 | I26: =IF(D26>0,H26/D26,0) -> 192.30769 | J26: =SUM($H$6:H26) -> 105000 | K26: =OreReserve-SUM($G$6:G26) -> 276470.59 | M26: 1 | N26: =SUMIF($B$6:$B$65,M26,$H$6:$H$65) -> 60000 | O26: =INDEX('الخطة الفنية والإنتاج'!$D$24:$H$24,M26) -> 60000 | P26: =N26-O26 -> 0
A27: =EDATE($N$21,C27-1) -> 47300 | B27: =INT((C27-1)/12)+1 -> 2 | C27: 22 | D27: =INDEX($N$6:$N$17,MONTH(A27)) -> 26 | E27: =INDEX('الخطة الفنية والإنتاج'!$D$20:$H$20,B27) -> 1 | F27: =IF($N$18>0,INDEX('الخطة الفنية والإنتاج'!$D$22:$H$22,B27)*D27/$N$18,0) -> 29411.765 | G27: =IF($N$18>0,INDEX('الخطة الفنية والإنتاج'!$D$23:$H$23,B27)*D27/$N$18,0) -> 5882.3529 | H27: =IF($N$18>0,INDEX('الخطة الفنية والإنتاج'!$D$24:$H$24,B27)*D27/$N$18,0) -> 5000 | I27: =IF(D27>0,H27/D27,0) -> 192.30769 | J27: =SUM($H$6:H27) -> 110000 | K27: =OreReserve-SUM($G$6:G27) -> 270588.24 | M27: 2 | N27: =SUMIF($B$6:$B$65,M27,$H$6:$H$65) -> 60000 | O27: =INDEX('الخطة الفنية والإنتاج'!$D$24:$H$24,M27) -> 60000 | P27: =N27-O27 -> 0
A28: =EDATE($N$21,C28-1) -> 47331 | B28: =INT((C28-1)/12)+1 -> 2 | C28: 23 | D28: =INDEX($N$6:$N$17,MONTH(A28)) -> 26 | E28: =INDEX('الخطة الفنية والإنتاج'!$D$20:$H$20,B28) -> 1 | F28: =IF($N$18>0,INDEX('الخطة الفنية والإنتاج'!$D$22:$H$22,B28)*D28/$N$18,0) -> 29411.765 | G28: =IF($N$18>0,INDEX('الخطة الفنية والإنتاج'!$D$23:$H$23,B28)*D28/$N$18,0) -> 5882.3529 | H28: =IF($N$18>0,INDEX('الخطة الفنية والإنتاج'!$D$24:$H$24,B28)*D28/$N$18,0) -> 5000 | I28: =IF(D28>0,H28/D28,0) -> 192.30769 | J28: =SUM($H$6:H28) -> 115000 | K28: =OreReserve-SUM($G$6:G28) -> 264705.88 | M28: 3 | N28: =SUMIF($B$6:$B$65,M28,$H$6:$H$65) -> 60000 | O28: =INDEX('الخطة الفنية والإنتاج'!$D$24:$H$24,M28) -> 60000 | P28: =N28-O28 -> 0
A29: =EDATE($N$21,C29-1) -> 47362 | B29: =INT((C29-1)/12)+1 -> 2 | C29: 24 | D29: =INDEX($N$6:$N$17,MONTH(A29)) -> 26 | E29: =INDEX('الخطة الفنية والإنتاج'!$D$20:$H$20,B29) -> 1 | F29: =IF($N$18>0,INDEX('الخطة الفنية والإنتاج'!$D$22:$H$22,B29)*D29/$N$18,0) -> 29411.765 | G29: =IF($N$18>0,INDEX('الخطة الفنية والإنتاج'!$D$23:$H$23,B29)*D29/$N$18,0) -> 5882.3529 | H29: =IF($N$18>0,INDEX('الخطة الفنية والإنتاج'!$D$24:$H$24,B29)*D29/$N$18,0) -> 5000 | I29: =IF(D29>0,H29/D29,0) -> 192.30769 | J29: =SUM($H$6:H29) -> 120000 | K29: =OreReserve-SUM($G$6:G29) -> 258823.53 | M29: 4 | N29: =SUMIF($B$6:$B$65,M29,$H$6:$H$65) -> 60000 | O29: =INDEX('الخطة الفنية والإنتاج'!$D$24:$H$24,M29) -> 60000 | P29: =N29-O29 -> 0
A30: =EDATE($N$21,C30-1) -> 47392 | B30: =INT((C30-1)/12)+1 -> 3 | C30: 25 | D30: =INDEX($N$6:$N$17,MONTH(A30)) -> 26 | E30: =INDEX('الخطة الفنية والإنتاج'!$D$20:$H$20,B30) -> 1 | F30: =IF($N$18>0,INDEX('الخطة الفنية والإنتاج'!$D$22:$H$22,B30)*D30/$N$18,0) -> 29411.765 | G30: =IF($N$18>0,INDEX('الخطة الفنية والإنتاج'!$D$23:$H$23,B30)*D30/$N$18,0) -> 5882.3529 | H30: =IF($N$18>0,INDEX('الخطة الفنية والإنتاج'!$D$24:$H$24,B30)*D30/$N$18,0) -> 5000 | I30: =IF(D30>0,H30/D30,0) -> 192.30769 | J30: =SUM($H$6:H30) -> 125000 | K30: =OreReserve-SUM($G$6:G30) -> 252941.18 | M30: 5 | N30: =SUMIF($B$6:$B$65,M30,$H$6:$H$65) -> 60000 | O30: =INDEX('الخطة الفنية والإنتاج'!$D$24:$H$24,M30) -> 60000 | P30: =N30-O30 -> 0
A31: =EDATE($N$21,C31-1) -> 47423 | B31: =INT((C31-1)/12)+1 -> 3 | C31: 26 | D31: =INDEX($N$6:$N$17,MONTH(A31)) -> 26 | E31: =INDEX('الخطة الفنية والإنتاج'!$D$20:$H$20,B31) -> 1 | F31: =IF($N$18>0,INDEX('الخطة الفنية والإنتاج'!$D$22:$H$22,B31)*D31/$N$18,0) -> 29411.765 | G31: =IF($N$18>0,INDEX('الخطة الفنية والإنتاج'!$D$23:$H$23,B31)*D31/$N$18,0) -> 5882.3529 | H31: =IF($N$18>0,INDEX('الخطة الفنية والإنتاج'!$D$24:$H$24,B31)*D31/$N$18,0) -> 5000 | I31: =IF(D31>0,H31/D31,0) -> 192.30769 | J31: =SUM($H$6:H31) -> 130000 | K31: =OreReserve-SUM($G$6:G31) -> 247058.82 | M31: الإجمالي | N31: =SUM(N26:N30) -> 300000 | O31: =SUM(O26:O30) -> 300000 | P31: =SUM(P26:P30) -> 0
A32: =EDATE($N$21,C32-1) -> 47453 | B32: =INT((C32-1)/12)+1 -> 3 | C32: 27 | D32: =INDEX($N$6:$N$17,MONTH(A32)) -> 26 | E32: =INDEX('الخطة الفنية والإنتاج'!$D$20:$H$20,B32) -> 1 | F32: =IF($N$18>0,INDEX('الخطة الفنية والإنتاج'!$D$22:$H$22,B32)*D32/$N$18,0) -> 29411.765 | G32: =IF($N$18>0,INDEX('الخطة الفنية والإنتاج'!$D$23:$H$23,B32)*D32/$N$18,0) -> 5882.3529 | H32: =IF($N$18>0,INDEX('الخطة الفنية والإنتاج'!$D$24:$H$24,B32)*D32/$N$18,0) -> 5000 | I32: =IF(D32>0,H32/D32,0) -> 192.30769 | J32: =SUM($H$6:H32) -> 135000 | K32: =OreReserve-SUM($G$6:G32) -> 241176.47 | M32: النتيجة | N32: =IF(SUMPRODUCT(ABS(P26:P30))<0.5,"مطابق","يوجد فرق — راجع التوزيع") -> مطابق
A33: =EDATE($N$21,C33-1) -> 47484 | B33: =INT((C33-1)/12)+1 -> 3 | C33: 28 | D33: =INDEX($N$6:$N$17,MONTH(A33)) -> 26 | E33: =INDEX('الخطة الفنية والإنتاج'!$D$20:$H$20,B33) -> 1 | F33: =IF($N$18>0,INDEX('الخطة الفنية والإنتاج'!$D$22:$H$22,B33)*D33/$N$18,0) -> 29411.765 | G33: =IF($N$18>0,INDEX('الخطة الفنية والإنتاج'!$D$23:$H$23,B33)*D33/$N$18,0) -> 5882.3529 | H33: =IF($N$18>0,INDEX('الخطة الفنية والإنتاج'!$D$24:$H$24,B33)*D33/$N$18,0) -> 5000 | I33: =IF(D33>0,H33/D33,0) -> 192.30769 | J33: =SUM($H$6:H33) -> 140000 | K33: =OreReserve-SUM($G$6:G33) -> 235294.12
A34: =EDATE($N$21,C34-1) -> 47515 | B34: =INT((C34-1)/12)+1 -> 3 | C34: 29 | D34: =INDEX($N$6:$N$17,MONTH(A34)) -> 26 | E34: =INDEX('الخطة الفنية والإنتاج'!$D$20:$H$20,B34) -> 1 | F34: =IF($N$18>0,INDEX('الخطة الفنية والإنتاج'!$D$22:$H$22,B34)*D34/$N$18,0) -> 29411.765 | G34: =IF($N$18>0,INDEX('الخطة الفنية والإنتاج'!$D$23:$H$23,B34)*D34/$N$18,0) -> 5882.3529 | H34: =IF($N$18>0,INDEX('الخطة الفنية والإنتاج'!$D$24:$H$24,B34)*D34/$N$18,0) -> 5000 | I34: =IF(D34>0,H34/D34,0) -> 192.30769 | J34: =SUM($H$6:H34) -> 145000 | K34: =OreReserve-SUM($G$6:G34) -> 229411.76
A35: =EDATE($N$21,C35-1) -> 47543 | B35: =INT((C35-1)/12)+1 -> 3 | C35: 30 | D35: =INDEX($N$6:$N$17,MONTH(A35)) -> 26 | E35: =INDEX('الخطة الفنية والإنتاج'!$D$20:$H$20,B35) -> 1 | F35: =IF($N$18>0,INDEX('الخطة الفنية والإنتاج'!$D$22:$H$22,B35)*D35/$N$18,0) -> 29411.765 | G35: =IF($N$18>0,INDEX('الخطة الفنية والإنتاج'!$D$23:$H$23,B35)*D35/$N$18,0) -> 5882.3529 | H35: =IF($N$18>0,INDEX('الخطة الفنية والإنتاج'!$D$24:$H$24,B35)*D35/$N$18,0) -> 5000 | I35: =IF(D35>0,H35/D35,0) -> 192.30769 | J35: =SUM($H$6:H35) -> 150000 | K35: =OreReserve-SUM($G$6:G35) -> 223529.41
A36: =EDATE($N$21,C36-1) -> 47574 | B36: =INT((C36-1)/12)+1 -> 3 | C36: 31 | D36: =INDEX($N$6:$N$17,MONTH(A36)) -> 26 | E36: =INDEX('الخطة الفنية والإنتاج'!$D$20:$H$20,B36) -> 1 | F36: =IF($N$18>0,INDEX('الخطة الفنية والإنتاج'!$D$22:$H$22,B36)*D36/$N$18,0) -> 29411.765 | G36: =IF($N$18>0,INDEX('الخطة الفنية والإنتاج'!$D$23:$H$23,B36)*D36/$N$18,0) -> 5882.3529 | H36: =IF($N$18>0,INDEX('الخطة الفنية والإنتاج'!$D$24:$H$24,B36)*D36/$N$18,0) -> 5000 | I36: =IF(D36>0,H36/D36,0) -> 192.30769 | J36: =SUM($H$6:H36) -> 155000 | K36: =OreReserve-SUM($G$6:G36) -> 217647.06
A37: =EDATE($N$21,C37-1) -> 47604 | B37: =INT((C37-1)/12)+1 -> 3 | C37: 32 | D37: =INDEX($N$6:$N$17,MONTH(A37)) -> 26 | E37: =INDEX('الخطة الفنية والإنتاج'!$D$20:$H$20,B37) -> 1 | F37: =IF($N$18>0,INDEX('الخطة الفنية والإنتاج'!$D$22:$H$22,B37)*D37/$N$18,0) -> 29411.765 | G37: =IF($N$18>0,INDEX('الخطة الفنية والإنتاج'!$D$23:$H$23,B37)*D37/$N$18,0) -> 5882.3529 | H37: =IF($N$18>0,INDEX('الخطة الفنية والإنتاج'!$D$24:$H$24,B37)*D37/$N$18,0) -> 5000 | I37: =IF(D37>0,H37/D37,0) -> 192.30769 | J37: =SUM($H$6:H37) -> 160000 | K37: =OreReserve-SUM($G$6:G37) -> 211764.71
A38: =EDATE($N$21,C38-1) -> 47635 | B38: =INT((C38-1)/12)+1 -> 3 | C38: 33 | D38: =INDEX($N$6:$N$17,MONTH(A38)) -> 26 | E38: =INDEX('الخطة الفنية والإنتاج'!$D$20:$H$20,B38) -> 1 | F38: =IF($N$18>0,INDEX('الخطة الفنية والإنتاج'!$D$22:$H$22,B38)*D38/$N$18,0) -> 29411.765 | G38: =IF($N$18>0,INDEX('الخطة الفنية والإنتاج'!$D$23:$H$23,B38)*D38/$N$18,0) -> 5882.3529 | H38: =IF($N$18>0,INDEX('الخطة الفنية والإنتاج'!$D$24:$H$24,B38)*D38/$N$18,0) -> 5000 | I38: =IF(D38>0,H38/D38,0) -> 192.30769 | J38: =SUM($H$6:H38) -> 165000 | K38: =OreReserve-SUM($G$6:G38) -> 205882.35
A39: =EDATE($N$21,C39-1) -> 47665 | B39: =INT((C39-1)/12)+1 -> 3 | C39: 34 | D39: =INDEX($N$6:$N$17,MONTH(A39)) -> 26 | E39: =INDEX('الخطة الفنية والإنتاج'!$D$20:$H$20,B39) -> 1 | F39: =IF($N$18>0,INDEX('الخطة الفنية والإنتاج'!$D$22:$H$22,B39)*D39/$N$18,0) -> 29411.765 | G39: =IF($N$18>0,INDEX('الخطة الفنية والإنتاج'!$D$23:$H$23,B39)*D39/$N$18,0) -> 5882.3529 | H39: =IF($N$18>0,INDEX('الخطة الفنية والإنتاج'!$D$24:$H$24,B39)*D39/$N$18,0) -> 5000 | I39: =IF(D39>0,H39/D39,0) -> 192.30769 | J39: =SUM($H$6:H39) -> 170000 | K39: =OreReserve-SUM($G$6:G39) -> 200000
A40: =EDATE($N$21,C40-1) -> 47696 | B40: =INT((C40-1)/12)+1 -> 3 | C40: 35 | D40: =INDEX($N$6:$N$17,MONTH(A40)) -> 26 | E40: =INDEX('الخطة الفنية والإنتاج'!$D$20:$H$20,B40) -> 1 | F40: =IF($N$18>0,INDEX('الخطة الفنية والإنتاج'!$D$22:$H$22,B40)*D40/$N$18,0) -> 29411.765 | G40: =IF($N$18>0,INDEX('الخطة الفنية والإنتاج'!$D$23:$H$23,B40)*D40/$N$18,0) -> 5882.3529 | H40: =IF($N$18>0,INDEX('الخطة الفنية والإنتاج'!$D$24:$H$24,B40)*D40/$N$18,0) -> 5000 | I40: =IF(D40>0,H40/D40,0) -> 192.30769 | J40: =SUM($H$6:H40) -> 175000 | K40: =OreReserve-SUM($G$6:G40) -> 194117.65
A41: =EDATE($N$21,C41-1) -> 47727 | B41: =INT((C41-1)/12)+1 -> 3 | C41: 36 | D41: =INDEX($N$6:$N$17,MONTH(A41)) -> 26 | E41: =INDEX('الخطة الفنية والإنتاج'!$D$20:$H$20,B41) -> 1 | F41: =IF($N$18>0,INDEX('الخطة الفنية والإنتاج'!$D$22:$H$22,B41)*D41/$N$18,0) -> 29411.765 | G41: =IF($N$18>0,INDEX('الخطة الفنية والإنتاج'!$D$23:$H$23,B41)*D41/$N$18,0) -> 5882.3529 | H41: =IF($N$18>0,INDEX('الخطة الفنية والإنتاج'!$D$24:$H$24,B41)*D41/$N$18,0) -> 5000 | I41: =IF(D41>0,H41/D41,0) -> 192.30769 | J41: =SUM($H$6:H41) -> 180000 | K41: =OreReserve-SUM($G$6:G41) -> 188235.29
A42: =EDATE($N$21,C42-1) -> 47757 | B42: =INT((C42-1)/12)+1 -> 4 | C42: 37 | D42: =INDEX($N$6:$N$17,MONTH(A42)) -> 26 | E42: =INDEX('الخطة الفنية والإنتاج'!$D$20:$H$20,B42) -> 1 | F42: =IF($N$18>0,INDEX('الخطة الفنية والإنتاج'!$D$22:$H$22,B42)*D42/$N$18,0) -> 29411.765 | G42: =IF($N$18>0,INDEX('الخطة الفنية والإنتاج'!$D$23:$H$23,B42)*D42/$N$18,0) -> 5882.3529 | H42: =IF($N$18>0,INDEX('الخطة الفنية والإنتاج'!$D$24:$H$24,B42)*D42/$N$18,0) -> 5000 | I42: =IF(D42>0,H42/D42,0) -> 192.30769 | J42: =SUM($H$6:H42) -> 185000 | K42: =OreReserve-SUM($G$6:G42) -> 182352.94
A43: =EDATE($N$21,C43-1) -> 47788 | B43: =INT((C43-1)/12)+1 -> 4 | C43: 38 | D43: =INDEX($N$6:$N$17,MONTH(A43)) -> 26 | E43: =INDEX('الخطة الفنية والإنتاج'!$D$20:$H$20,B43) -> 1 | F43: =IF($N$18>0,INDEX('الخطة الفنية والإنتاج'!$D$22:$H$22,B43)*D43/$N$18,0) -> 29411.765 | G43: =IF($N$18>0,INDEX('الخطة الفنية والإنتاج'!$D$23:$H$23,B43)*D43/$N$18,0) -> 5882.3529 | H43: =IF($N$18>0,INDEX('الخطة الفنية والإنتاج'!$D$24:$H$24,B43)*D43/$N$18,0) -> 5000 | I43: =IF(D43>0,H43/D43,0) -> 192.30769 | J43: =SUM($H$6:H43) -> 190000 | K43: =OreReserve-SUM($G$6:G43) -> 176470.59
A44: =EDATE($N$21,C44-1) -> 47818 | B44: =INT((C44-1)/12)+1 -> 4 | C44: 39 | D44: =INDEX($N$6:$N$17,MONTH(A44)) -> 26 | E44: =INDEX('الخطة الفنية والإنتاج'!$D$20:$H$20,B44) -> 1 | F44: =IF($N$18>0,INDEX('الخطة الفنية والإنتاج'!$D$22:$H$22,B44)*D44/$N$18,0) -> 29411.765 | G44: =IF($N$18>0,INDEX('الخطة الفنية والإنتاج'!$D$23:$H$23,B44)*D44/$N$18,0) -> 5882.3529 | H44: =IF($N$18>0,INDEX('الخطة الفنية والإنتاج'!$D$24:$H$24,B44)*D44/$N$18,0) -> 5000 | I44: =IF(D44>0,H44/D44,0) -> 192.30769 | J44: =SUM($H$6:H44) -> 195000 | K44: =OreReserve-SUM($G$6:G44) -> 170588.24
... A65: =EDATE($N$21,C65-1) -> 48458 | B65: =INT((C65-1)/12)+1 -> 5 | C65: 60 | D65: =INDEX($N$6:$N$17,MONTH(A65)) -> 26 | E65: =INDEX('الخطة الفنية والإنتاج'!$D$20:$H$20,B65) -> 1 | F65: =IF($N$18>0,INDEX('الخطة الفنية والإنتاج'!$D$22:$H$22,B65)*D65/$N$18,0) -> 29411.765 | G65: =IF($N$18>0,INDEX('الخطة الفنية والإنتاج'!$D$23:$H$23,B65)*D65/$N$18,0) -> 5882.3529 | H65: =IF($N$18>0,INDEX('الخطة الفنية والإنتاج'!$D$24:$H$24,B65)*D65/$N$18,0) -> 5000 | I65: =IF(D65>0,H65/D65,0) -> 192.30769 | J65: =SUM($H$6:H65) -> 300000 | K65: =OreReserve-SUM($G$6:G65) -> 47058.824
A66: الإجمالي (5 سنوات) | D66: =SUM(D6:D65) -> 1560 | F66: =SUM(F6:F65) -> 1764705.9 | G66: =SUM(G6:G65) -> 352941.18 | H66: =SUM(H6:H65) -> 300000

Sheet الجدول الزمني
A1: مراحل وخطة تنفيذ المشروع
A2: التسلسل الصحيح: استكشاف ← دراسات وتراخيص ← تمويل وتجهيز ← تأهيل الموقع ← إنتاج. المدد تقديرية وتُعدَّل من عمودي «شهر البداية» و«المدة»
A4: المهمة | B4: الجهة / التفاصيل | C4: شهر البداية | D4: المدة (شهر) | E4: تاريخ البداية | F4: تاريخ النهاية | G4: 1 | H4: 2 | I4: 3 | J4: 4 | K4: 5 | L4: 6 | M4: 7 | N4: 8 | O4: 9 | P4: 10 | Q4: 11 | R4: 12
A5: المرحلة التمهيدية — الاستكشاف (منجزة)
A6: ترخيص التنقيب والتصريح البيئي للتنقيب | B6: وزارة الطاقة والمعادن / هيئة البيئة — منجز
A7: فتح الطريق وأعمال التنقيب وأخذ العينات | B7: منجز خلال السنوات الثلاث الماضية (مصاريف مدفوعة سابقاً)
A8: المرحلة الأولى — الدراسات والتراخيص
A9: التقرير الاستكشافي وتقدير الاحتياطي والدرجة | B9: جيولوجي معتمد / مختبر تحاليل | C9: 1 | D9: 2 | E9: =IF($D9>0,EDATE(StartDate,$C9-1),"") -> 46388 | F9: =IF($D9>0,EDATE(StartDate,$C9-1+$D9)-1,"") -> 46446
A10: دراسة الجدوى وخطة التعدين والمخططات الهندسية | B10: مكتب استشاري | C10: 1 | D10: 2 | E10: =IF($D10>0,EDATE(StartDate,$C10-1),"") -> 46388 | F10: =IF($D10>0,EDATE(StartDate,$C10-1+$D10)-1,"") -> 46446
A11: دراسة الأثر البيئي والتصريح البيئي للتعدين | B11: هيئة البيئة | C11: 2 | D11: 3 | E11: =IF($D11>0,EDATE(StartDate,$C11-1),"") -> 46419 | F11: =IF($D11>0,EDATE(StartDate,$C11-1+$D11)-1,"") -> 46507
A12: طلب ترخيص التعدين وموافقات الجهات المختصة | B12: وزارة الطاقة والمعادن | C12: 3 | D12: 4 | E12: =IF($D12>0,EDATE(StartDate,$C12-1),"") -> 46447 | F12: =IF($D12>0,EDATE(StartDate,$C12-1+$D12)-1,"") -> 46568
A13: تقديم الضمانات البنكية | B13: البنك / وزارة الطاقة والمعادن / هيئة البيئة | C13: 6 | D13: 1 | E13: =IF($D13>0,EDATE(StartDate,$C13-1),"") -> 46539 | F13: =IF($D13>0,EDATE(StartDate,$C13-1+$D13)-1,"") -> 46568
A14: الترخيص البلدي | B14: بلدية شمال الشرقية | C14: 6 | D14: 1 | E14: =IF($D14>0,EDATE(StartDate,$C14-1),"") -> 46539 | F14: =IF($D14>0,EDATE(StartDate,$C14-1+$D14)-1,"") -> 46568
A15: المرحلة الثانية — التمويل والتجهيز | E15: =IF($D15>0,EDATE(StartDate,$C15-1),"") | F15: =IF($D15>0,EDATE(StartDate,$C15-1+$D15)-1,"")
A16: اعتماد التمويل وتوقيع عقد القرض | B16: الجهة الممولة | C16: 5 | D16: 2 | E16: =IF($D16>0,EDATE(StartDate,$C16-1),"") -> 46508 | F16: =IF($D16>0,EDATE(StartDate,$C16-1+$D16)-1,"") -> 46568
A17: التعاقد على بيع وتسويق الخام | B17: شركة متاجرة المعادن / مشترون محليون | C17: 6 | D17: 2 | E17: =IF($D17>0,EDATE(StartDate,$C17-1),"") -> 46539 | F17: =IF($D17>0,EDATE(StartDate,$C17-1+$D17)-1,"") -> 46599
A18: استئجار السكن والمكتب وموقع التجميع | B18: 3 مواقع | C18: 7 | D18: 1 | E18: =IF($D18>0,EDATE(StartDate,$C18-1),"") -> 46569 | F18: =IF($D18>0,EDATE(StartDate,$C18-1+$D18)-1,"") -> 46599
A19: توظيف الكادر العُماني | B19: مدير، محاسب، جيولوجي، مشرفان، سائق، 4 حراس | C19: 7 | D19: 2 | E19: =IF($D19>0,EDATE(StartDate,$C19-1),"") -> 46569 | F19: =IF($D19>0,EDATE(StartDate,$C19-1+$D19)-1,"") -> 46630
A20: استخراج مأذونيات العمالة الوافدة والتأشيرات | B20: ="وزارة العمل / شرطة عُمان السلطانية — "&'الموارد البشرية'!B21&" عاملاً" -> وزارة العمل / شرطة عُمان السلطانية — 8 عاملاً | C20: 7 | D20: 2 | E20: =IF($D20>0,EDATE(StartDate,$C20-1),"") -> 46569 | F20: =IF($D20>0,EDATE(StartDate,$C20-1+$D20)-1,"") -> 46630
A21: شراء الشيول والقلاب والبيك أب | B21: معدات مملوكة | C21: 7 | D21: 2 | E21: =IF($D21>0,EDATE(StartDate,$C21-1),"") -> 46569 | F21: =IF($D21>0,EDATE(StartDate,$C21-1+$D21)-1,"") -> 46630
A22: شراء معدات الأمن والسلامة والأجهزة والأثاث | B22: — | C22: 8 | D22: 1 | E22: =IF($D22>0,EDATE(StartDate,$C22-1),"") -> 46600 | F22: =IF($D22>0,EDATE(StartDate,$C22-1+$D22)-1,"") -> 46630
A23: التعاقد على استئجار الحفارات والمولد | B23: 5 حفارات بالساعة شاملة المشغل والديزل + مولد | C23: 9 | D23: 1 | E23: =IF($D23>0,EDATE(StartDate,$C23-1),"") -> 46631 | F23: =IF($D23>0,EDATE(StartDate,$C23-1+$D23)-1,"") -> 46660
A24: المرحلة الثالثة — تأهيل الموقع | E24: =IF($D24>0,EDATE(StartDate,$C24-1),"") | F24: =IF($D24>0,EDATE(StartDate,$C24-1+$D24)-1,"")
A25: تأهيل الطريق المؤدي إلى الموقع | B25: — | C25: 8 | D25: 1 | E25: =IF($D25>0,EDATE(StartDate,$C25-1),"") -> 46600 | F25: =IF($D25>0,EDATE(StartDate,$C25-1+$D25)-1,"") -> 46630
A26: تجهيز الموقع وإزالة الغطاء الصخري (التعرية الأولية) | B26: — | C26: 8 | D26: 2 | E26: =IF($D26>0,EDATE(StartDate,$C26-1),"") -> 46600 | F26: =IF($D26>0,EDATE(StartDate,$C26-1+$D26)-1,"") -> 46660
A27: المرحلة الرابعة — الإنتاج | E27: =IF($D27>0,EDATE(StartDate,$C27-1),"") | F27: =IF($D27>0,EDATE(StartDate,$C27-1+$D27)-1,"")
A28: الإنتاج التجريبي ثم التجاري (بداية السنة الأولى في الدراسة) | B28: بيع أولى الشحنات | C28: 10 | D28: 3 | E28: =IF($D28>0,EDATE(StartDate,$C28-1),"") -> 46661 | F28: =IF($D28>0,EDATE(StartDate,$C28-1+$D28)-1,"") -> 46752
A30: مدة التأسيس حتى بدء الإنتاج | C30: =C28-1 -> 9 | D30: شهر
A31: ملاحظة: مدة إصدار ترخيص التعدين تتفاوت كثيراً بحسب موافقات الجهات المختصة — يُنصح بهامش زمني إضافي عند الالتزام مع الممولين والمورّدين.

Sheet الأصول والإهلاك
A1: الأصول الثابتة وجدول الإهلاك
A2: إهلاك بطريقة القسط الثابت. الحفارات مستأجرة بالساعة (انظر «الإيجارات»)؛ الشيول والقلاب والبيك أب مملوكة
A4: الأصل | B4: العدد | C4: سعر الوحدة (ر.ع) | D4: التكلفة الإجمالية | E4: العمر الإنتاجي (سنة) | F4: القيمة التخريدية % | G4: يُستبدل عند انتهاء العمر (1 = نعم) | H4: الإهلاك السنوي | I4: المصدر / ملاحظات
A5: شيول (لودر بعجلات) | B5: 1 | C5: 50000 | D5: =B5*C5*F_Capex -> 50000 | E5: 7 | F5: 0.15 | G5: 0 | H5: =IF(E5>0,D5*(1-F5)/E5,0) -> 6071.4286 | I5: شراء بقرار المالك — السعر افتراض يُؤكَّد بعروض الوكلاء
A6: قلاب (تيبر) لنقل الخام | B6: 1 | C6: 32000 | D6: =B6*C6*F_Capex -> 32000 | E6: 7 | F6: 0.15 | G6: 0 | H6: =IF(E6>0,D6*(1-F6)/E6,0) -> 3885.7143 | I6: شراء بقرار المالك — السعر افتراض يُؤكَّد بعروض الوكلاء
A7: سيارة بيك أب دفع رباعي | B7: 1 | C7: 11000 | D7: =B7*C7*F_Capex -> 11000 | E7: 5 | F7: 0.2 | G7: 0 | H7: =IF(E7>0,D7*(1-F7)/E7,0) -> 1760 | I7: شراء بقرار المالك — السعر افتراض يُؤكَّد بعرض
A8: أثاث وتجهيزات المكتب والسكن | B8: 1 | C8: 4000 | D8: =B8*C8*F_Capex -> 4000 | E8: 5 | F8: 0 | G8: 0 | H8: =IF(E8>0,D8*(1-F8)/E8,0) -> 800 | I8: 4,000 من الدراسة الأصلية
A9: معدات الأمن والسلامة والأجهزة | B9: 1 | C9: 3500 | D9: =B9*C9*F_Capex -> 3500 | E9: 5 | F9: 0 | G9: 0 | H9: =IF(E9>0,D9*(1-F9)/E9,0) -> 700 | I9: افتراض يُؤكَّد بعرض سعر
A10: إجمالي الأصول الثابتة | D10: =SUM(D5:D9) -> 100500 | H10: =SUM(H5:H9) -> 13217.143
A11: منها: المعدات والمركبات المتحركة | D11: =SUM(D5:D7) -> 93000 | I11: أساس احتساب الصيانة والتأمين
A13: جدول الإهلاك والاستبدال | B13: الوحدة | C13: 0 | D13: 1 | E13: 2 | F13: 3 | G13: 4 | H13: 5 | I13: الإجمالي
A14: إهلاك شيول (لودر بعجلات) | B14: ر.ع | D14: =IF(OR(D$13<=$E$5,$G$5=1),$H$5,0) -> 6071.4286 | E14: =IF(OR(E$13<=$E$5,$G$5=1),$H$5,0) -> 6071.4286 | F14: =IF(OR(F$13<=$E$5,$G$5=1),$H$5,0) -> 6071.4286 | G14: =IF(OR(G$13<=$E$5,$G$5=1),$H$5,0) -> 6071.4286 | H14: =IF(OR(H$13<=$E$5,$G$5=1),$H$5,0) -> 6071.4286 | I14: =SUM(D14:H14) -> 30357.143
A15: إهلاك قلاب (تيبر) لنقل الخام | B15: ر.ع | D15: =IF(OR(D$13<=$E$6,$G$6=1),$H$6,0) -> 3885.7143 | E15: =IF(OR(E$13<=$E$6,$G$6=1),$H$6,0) -> 3885.7143 | F15: =IF(OR(F$13<=$E$6,$G$6=1),$H$6,0) -> 3885.7143 | G15: =IF(OR(G$13<=$E$6,$G$6=1),$H$6,0) -> 3885.7143 | H15: =IF(OR(H$13<=$E$6,$G$6=1),$H$6,0) -> 3885.7143 | I15: =SUM(D15:H15) -> 19428.571
A16: إهلاك سيارة بيك أب دفع رباعي | B16: ر.ع | D16: =IF(OR(D$13<=$E$7,$G$7=1),$H$7,0) -> 1760 | E16: =IF(OR(E$13<=$E$7,$G$7=1),$H$7,0) -> 1760 | F16: =IF(OR(F$13<=$E$7,$G$7=1),$H$7,0) -> 1760 | G16: =IF(OR(G$13<=$E$7,$G$7=1),$H$7,0) -> 1760 | H16: =IF(OR(H$13<=$E$7,$G$7=1),$H$7,0) -> 1760 | I16: =SUM(D16:H16) -> 8800
A17: إهلاك أثاث وتجهيزات المكتب والسكن | B17: ر.ع | D17: =IF(OR(D$13<=$E$8,$G$8=1),$H$8,0) -> 800 | E17: =IF(OR(E$13<=$E$8,$G$8=1),$H$8,0) -> 800 | F17: =IF(OR(F$13<=$E$8,$G$8=1),$H$8,0) -> 800 | G17: =IF(OR(G$13<=$E$8,$G$8=1),$H$8,0) -> 800 | H17: =IF(OR(H$13<=$E$8,$G$8=1),$H$8,0) -> 800 | I17: =SUM(D17:H17) -> 4000
A18: إهلاك معدات الأمن والسلامة والأجهزة | B18: ر.ع | D18: =IF(OR(D$13<=$E$9,$G$9=1),$H$9,0) -> 700 | E18: =IF(OR(E$13<=$E$9,$G$9=1),$H$9,0) -> 700 | F18: =IF(OR(F$13<=$E$9,$G$9=1),$H$9,0) -> 700 | G18: =IF(OR(G$13<=$E$9,$G$9=1),$H$9,0) -> 700 | H18: =IF(OR(H$13<=$E$9,$G$9=1),$H$9,0) -> 700 | I18: =SUM(D18:H18) -> 3500
A19: إجمالي الإهلاك السنوي | B19: ر.ع | D19: =SUM(D14:D18) -> 13217.143 | E19: =SUM(E14:E18) -> 13217.143 | F19: =SUM(F14:F18) -> 13217.143 | G19: =SUM(G14:G18) -> 13217.143 | H19: =SUM(H14:H18) -> 13217.143 | I19: =SUM(D19:H19) -> 66085.714
A20: استبدال الأصول (نفقات رأسمالية) | B20: ر.ع | D20: =IF(AND($G$5=1,D$13=$E$5+1),$D$5,0)+IF(AND($G$6=1,D$13=$E$6+1),$D$6,0)+IF(AND($G$7=1,D$13=$E$7+1),$D$7,0)+IF(AND($G$8=1,D$13=$E$8+1),$D$8,0)+IF(AND($G$9=1,D$13=$E$9+1),$D$9,0) -> 0 | E20: =IF(AND($G$5=1,E$13=$E$5+1),$D$5,0)+IF(AND($G$6=1,E$13=$E$6+1),$D$6,0)+IF(AND($G$7=1,E$13=$E$7+1),$D$7,0)+IF(AND($G$8=1,E$13=$E$8+1),$D$8,0)+IF(AND($G$9=1,E$13=$E$9+1),$D$9,0) -> 0 | F20: =IF(AND($G$5=1,F$13=$E$5+1),$D$5,0)+IF(AND($G$6=1,F$13=$E$6+1),$D$6,0)+IF(AND($G$7=1,F$13=$E$7+1),$D$7,0)+IF(AND($G$8=1,F$13=$E$8+1),$D$8,0)+IF(AND($G$9=1,F$13=$E$9+1),$D$9,0) -> 0 | G20: =IF(AND($G$5=1,G$13=$E$5+1),$D$5,0)+IF(AND($G$6=1,G$13=$E$6+1),$D$6,0)+IF(AND($G$7=1,G$13=$E$7+1),$D$7,0)+IF(AND($G$8=1,G$13=$E$8+1),$D$8,0)+IF(AND($G$9=1,G$13=$E$9+1),$D$9,0) -> 0 | H20: =IF(AND($G$5=1,H$13=$E$5+1),$D$5,0)+IF(AND($G$6=1,H$13=$E$6+1),$D$6,0)+IF(AND($G$7=1,H$13=$E$7+1),$D$7,0)+IF(AND($G$8=1,H$13=$E$8+1),$D$8,0)+IF(AND($G$9=1,H$13=$E$9+1),$D$9,0) -> 0 | I20: =SUM(D20:H20) -> 0
A21: الأصول بالتكلفة (تراكمي) | B21: ر.ع | C21: =D10 -> 100500 | D21: =C21+D20 -> 100500 | E21: =D21+E20 -> 100500 | F21: =E21+F20 -> 100500 | G21: =F21+G20 -> 100500 | H21: =G21+H20 -> 100500
A22: مجمع الإهلاك | B22: ر.ع | C22: 0 | D22: =C22+D19 -> 13217.143 | E22: =D22+E19 -> 26434.286 | F22: =E22+F19 -> 39651.429 | G22: =F22+G19 -> 52868.571 | H22: =G22+H19 -> 66085.714
A23: صافي القيمة الدفترية آخر السنة | B23: ر.ع | C23: =C21-C22 -> 100500 | D23: =D21-D22 -> 87282.857 | E23: =E21-E22 -> 74065.714 | F23: =F21-F22 -> 60848.571 | G23: =G21-G22 -> 47631.429 | H23: =H21-H22 -> 34414.286
A24: صافي القيمة الدفترية في نهاية السنة الخامسة يُدرج كقيمة تخريدية في التدفقات النقدية.

Sheet مصاريف ما قبل التشغيل
A1: مصاريف ما قبل التشغيل
A2: تُرسمل وتُطفأ على سنوات التشغيل. الضمانات البنكية نُقلت إلى التكلفة الاستثمارية كوديعة مستردة
A4: البيان | B4: القيمة (ر.ع) | C4: الحالة | D4: ملاحظات
A5: رسوم التراخيص اللازمة للمشروع | B5: =LicFees -> 8400 | C5: محتسب | D5: من ورقة «التراخيص» (كان رابطاً خارجياً مكسوراً يعطي صفراً في الملف الأصلي)
A6: الاستشارات الإدارية والمالية والفنية | B6: 12200 | C6: من الدراسة الأصلية
A7: المخططات الهندسية والتصميمية | B7: 5600 | C7: من الدراسة الأصلية
A8: تكلفة مأذونيات استقدام العمالة الوافدة | B8: =PermitCost -> 2028 | C8: محتسب | D8: من ورقة «الموارد البشرية» وفق رسوم وزارة العمل (الملف الأصلي ذكر 3,420 في ورقة و2,420 في أخرى)
A9: مصاريف الاستكشاف وفتح الطريق والمعدات المدفوعة خلال السنوات الثلاث الماضية | B9: 200000 | C9: يحتاج تأكيداً | D9: الملف الأصلي ذكر 200,000 في ورقة و257,000 في أخرى — اعتُمد 200,000 ويجب تأكيد الرقم الصحيح بالمستندات
A10: الإجمالي | B10: =SUM(B5:B9) -> 228228
A12: مدة الإطفاء | B12: 5 | C12: سنة | D12: على مدة الدراسة (5 سنوات تشغيل)
A13: الإطفاء السنوي | B13: =PreOp/AmortYrs -> 45645.6 | C13: ر.ع / سنة

Sheet الموارد البشرية
A1: الموارد البشرية — الأجور والرواتب والتأمينات
A2: الوظائف والأعداد والرواتب من الدراسة الأصلية (مع تصحيح راتب الحارس إلى الحد الأدنى للأجور)
A4: الوظيفة | B4: الفئة | C4: الجنسية | D4: العدد | E4: الراتب الشهري (ر.ع) | F4: إجمالي الرواتب الشهرية | G4: الإجمالي السنوي | H4: فئة مأذونية العمل | I4: ملاحظات
A5: مدير المشروع | B5: إدارية | C5: عماني | D5: 1 | E5: 1300 | F5: =D5*E5 -> 1300 | G5: =F5*12 -> 15600
A6: محاسب | B6: إدارية | C6: عماني | D6: 1 | E6: 500 | F6: =D6*E6 -> 500 | G6: =F6*12 -> 6000
A7: سائق | B7: إدارية | C7: عماني | D7: 1 | E7: 350 | F7: =D7*E7 -> 350 | G7: =F7*12 -> 4200
A8: حارس | B8: إدارية | C8: عماني | D8: 4 | E8: 325 | F8: =D8*E8 -> 1300 | G8: =F8*12 -> 15600 | I8: في الأصل 320 ر.ع — رُفع إلى الحد الأدنى للأجور 325 ر.ع
A9: مهندس جيولوجي | B9: فنية | C9: عماني | D9: 1 | E9: 800 | F9: =D9*E9 -> 800 | G9: =F9*12 -> 9600
A10: مشرف الأمن والسلامة | B10: فنية | C10: عماني | D10: 1 | E10: 550 | F10: =D10*E10 -> 550 | G10: =F10*12 -> 6600
A11: مشرف عمليات | B11: فنية | C11: عماني | D11: 1 | E11: 450 | F11: =D11*E11 -> 450 | G11: =F11*12 -> 5400
A12: عامل فرز وتنقية الخام | B12: فنية | C12: وافد | D12: 5 | E12: 150 | F12: =D12*E12 -> 750 | G12: =F12*12 -> 9000 | H12: 3 | I12: ورد في الأصل باسم «عمال صقل أحجار»
A13: مشغل حفار | B13: فنية | C13: وافد | D13: 0 | E13: 250 | F13: =D13*E13 -> 0 | G13: =F13*12 -> 0 | H13: 2 | I13: مشمولون في إيجار الحفارات بالساعة (شامل المشغل) — أبقي الصف للمرجعية
A14: مشغل شيول | B14: فنية | C14: وافد | D14: 1 | E14: 250 | F14: =D14*E14 -> 250 | G14: =F14*12 -> 3000 | H14: 2
A15: سائق قلاب (تيبر) | B15: فنية | C15: وافد | D15: 1 | E15: 250 | F15: =D15*E15 -> 250 | G15: =F15*12 -> 3000 | H15: 2
A16: طباخ | B16: فنية | C16: وافد | D16: 1 | E16: 170 | F16: =D16*E16 -> 170 | G16: =F16*12 -> 2040 | H16: 3
A17: الإجمالي | D17: =SUM(D5:D16) -> 18 | F17: =SUM(F5:F16) -> 6670 | G17: =SUM(G5:G16) -> 80040
A19: ثانياً: ملخص العمالة
A20: عدد العُمانيين | B20: =SUMIF($C$5:$C$16,"عماني",$D$5:$D$16) -> 10 | C20: عامل
A21: عدد الوافدين | B21: =SUMIF($C$5:$C$16,"وافد",$D$5:$D$16) -> 8 | C21: عامل
A22: نسبة التعمين | B22: =B20/(B20+B21) -> 0.55555556 | C22: %
A23: رواتب العُمانيين السنوية | B23: =SUMIF($C$5:$C$16,"عماني",$G$5:$G$16) -> 63000 | C23: ر.ع
A24: رواتب الوافدين السنوية | B24: =SUMIF($C$5:$C$16,"وافد",$G$5:$G$16) -> 17040 | C24: ر.ع
A25: رواتب العمالة الإدارية السنوية | B25: =SUMIF($B$5:$B$16,"إدارية",$G$5:$G$16) -> 41400 | C25: ر.ع
A26: رواتب العمالة الفنية السنوية | B26: =SUMIF($B$5:$B$16,"فنية",$G$5:$G$16) -> 38640 | C26: ر.ع
A27: التحقق من الحد الأدنى لأجور العُمانيين | B27: =IF(COUNTIFS($C$5:$C$16,"عماني",$E$5:$E$16,"<"&MinWage)=0,"مطابق","يوجد راتب أقل من الحد الأدنى") -> مطابق
A29: ثالثاً: التأمينات والاشتراكات السنوية على صاحب العمل
A30: صندوق الحماية الاجتماعية — العُمانيون | B30: =B23*SPFOm -> 9135 | C30: ر.ع
A31: اشتراكات الحماية الاجتماعية — الوافدون | B31: =B24*SPFEx -> 511.2 | C31: ر.ع
A32: مخصص نهاية الخدمة / الادخار للوافدين | B32: =B24*EosRate -> 1533.6 | C32: ر.ع
A33: التأمين الصحي وتأمين العمال للوافدين | B33: =B21*ExpIns -> 3200 | C33: ر.ع
A34: إجمالي التأمينات والاشتراكات | B34: =SUM(B30:B33) -> 14379.8
A35: للمقارنة: الدراسة الأصلية قدّرت التأمينات بـ 7,880 ر.ع فقط (3,080 للعُمانيين — أقل من النسبة النظامية 14.5%).
A37: رابعاً: مأذونيات العمل للوافدين
A38: عدد مأذونيات الفئة الثانية | B38: =SUMIF($H$5:$H$16,2,$D$5:$D$16) -> 2 | C38: مأذونية
A39: عدد مأذونيات الفئة الثالثة | B39: =SUMIF($H$5:$H$16,3,$D$5:$D$16) -> 6 | C39: مأذونية
A40: رسوم المأذونيات (تتجدد كل سنتين) | B40: =B38*Permit2+B39*Permit3 -> 1708 | C40: ر.ع
A41: مصاريف استقدام أخرى | B41: =B21*PermitOther -> 320 | C41: ر.ع
A42: إجمالي تكلفة الاستقدام الأولي | B42: =B40+B41 -> 2028

Sheet الإيجارات
A1: الإيجارات — المواقع والمعدات والمركبات
A2: الحفارات مستأجرة بالساعة شاملة المعدة والمشغل والديزل؛ الشيول والقلاب والبيك أب مملوكة (انظر «الأصول والإهلاك»)
A4: البند | B4: العدد | C4: الإيجار الشهري للوحدة (ر.ع) | D4: عدد الأشهر | E4: الإجمالي السنوي | F4: المصدر / ملاحظات
A5: أولاً: إيجار المواقع
A6: سكن العمال | B6: 1 | C6: 200 | D6: 12 | E6: =B6*C6*D6 -> 2400 | F6: من الدراسة الأصلية
A7: المكتب | B7: 1 | C7: 250 | D7: 12 | E7: =B7*C7*D7 -> 3000 | F7: من الدراسة الأصلية
A8: موقع تجميع الخام | B8: 1 | C8: 400 | D8: 12 | E8: =B8*C8*D8 -> 4800 | F8: من الدراسة الأصلية
A9: إجمالي إيجار المواقع السنوي | E9: =SUM(E6:E8) -> 10200
A10: ثانياً: إيجار المعدات الشهري
A11: مولد كهرباء | B11: 1 | C11: 40 | D11: 12 | E11: =B11*C11*D11 -> 480 | F11: من الدراسة الأصلية
A12: إجمالي إيجار المعدات الشهري السنوي | E12: =SUM(E11:E11) -> 480
A14: ثالثاً: إيجار الحفارات بالساعة (شامل المعدة والمشغل والديزل)
A15: البند | B15: العدد | C15: أجرة الساعة (ر.ع) | D15: الساعات المجدولة للحفار سنوياً | E15: الإجمالي السنوي | F15: المصدر / ملاحظات
A16: حفار مع مشغل وديزل | B16: =ExcavNo -> 5 | C16: =HireRate -> 12 | D16: =SchedHrs -> 3120 | E16: =B16*C16*D16 -> 187200 | F16: معطى من المالك: 5 حفارات × 12 ر.ع/ساعة × 10 ساعات × 312 يوماً
A17: قبل نسبة استغلال الطاقة وأعباء تتبع العروق — تُطبَّق سنوياً في «التكاليف التشغيلية» عبر ساعات الإيجار في «الخطة الفنية والإنتاج».
A19: إجمالي الإيجارات السنوية (السنة الأولى، قبل الأعباء) | E19: =SiteRent+EquipRent+ExcavHire -> 197880

Sheet المواد المستهلكة
A1: الوقود والمواد المستهلكة (عند الطاقة الكاملة)
A2: وقود الحفارات مشمول في إيجارها بالساعة. «متغير» يتناسب مع نسبة استغلال الطاقة وأعباء تتبع العروق و«ثابت» لا يتغير
A4: المعدة / البند | B4: العدد / الأساس | C4: المعدل | D4: ساعات التشغيل السنوية | E4: الكمية السنوية (لتر) | F4: التكلفة السنوية (ر.ع) | G4: النوع | H4: ملاحظات
A5: أولاً: الوقود (ديزل) للمعدات المملوكة والمولد — المعدل باللتر في الساعة
A6: شيول | B6: ='الأصول والإهلاك'!B5 -> 1 | C6: 16 | D6: =OpHours -> 2340 | E6: =B6*C6*D6 -> 37440 | F6: =E6*DieselPrice -> 9659.52 | G6: متغير | H6: معدل الاستهلاك افتراض يُراجَع من بيانات الشركة المصنّعة
A7: قلاب | B7: ='الأصول والإهلاك'!B6 -> 1 | C7: 10 | D7: =OpHours -> 2340 | E7: =B7*C7*D7 -> 23400 | F7: =E7*DieselPrice -> 6037.2 | G7: متغير
A8: مولد كهرباء | B8: =الإيجارات!B11 -> 1 | C8: 3 | D8: 4380 | E8: =B8*C8*D8 -> 13140 | F8: =E8*DieselPrice -> 3390.12 | G8: ثابت | H8: 12 ساعة يومياً × 365 يوماً
A9: سيارة بيك أب | B9: ='الأصول والإهلاك'!B7 -> 1 | C9: 1.25 | D9: =WorkDays*ShiftHrs -> 3120 | E9: =B9*C9*D9 -> 3900 | F9: =E9*DieselPrice -> 1006.2 | G9: ثابت | H9: نحو 12.5 لتراً يومياً
A10: إجمالي الوقود | E10: =SUM(E6:E9) -> 77880 | F10: =SUM(F6:F9) -> 20093.04
A11: ثانياً: مواد ومستلزمات أخرى
A12: زيوت وشحوم وفلاتر | B12: % من الوقود | C12: 0.1 | F12: =C12*F10 -> 2009.304 | G12: متغير | H12: افتراض. قطع استهلاك الكسارات والأسنان مشمولة في إيجار الحفارات
A13: إطارات (شيول، قلاب، بيك أب) | B13: ر.ع / سنة | C13: 3600 | F13: =C13 -> 3600 | G13: متغير | H13: افتراض
A14: مستلزمات السلامة والوقاية الشخصية | B14: ر.ع / سنة | C14: 1500 | F14: =C14 -> 1500 | G14: ثابت | H14: افتراض
A15: مياه (صهاريج) للموقع والسكن | B15: ر.ع / شهر | C15: 250 | F15: =C15*12 -> 3000 | G15: ثابت | H15: افتراض
A16: تموين وإعاشة العمالة الوافدة | B16: ر.ع / عامل / شهر | C16: 25 | F16: =C16*12*'الموارد البشرية'!B21 -> 2400 | G16: ثابت | H16: افتراض
A17: إجمالي المواد المستهلكة عند الطاقة الكاملة | F17: =F10+SUM(F12:F16) -> 32602.344
A18: منها: تكاليف متغيرة | F18: =SUMIF(G6:G16,"متغير",F6:F16) -> 21306.024
A19: منها: تكاليف ثابتة | F19: =SUMIF(G6:G16,"ثابت",F6:F16) -> 11296.32

Sheet الإيرادات
A1: الإيرادات السنوية
A2: الكمية من «الخطة الفنية والإنتاج» والسعر من «السوق والسعر»
A4: البند | B4: الوحدة | C4: 0 | D4: 1 | E4: 2 | F4: 3 | G4: 4 | H4: 5 | I4: الإجمالي
A5: الكمية المباعة | B5: طن | D5: ='الخطة الفنية والإنتاج'!D24 -> 60000 | E5: ='الخطة الفنية والإنتاج'!E24 -> 60000 | F5: ='الخطة الفنية والإنتاج'!F24 -> 60000 | G5: ='الخطة الفنية والإنتاج'!G24 -> 60000 | H5: ='الخطة الفنية والإنتاج'!H24 -> 60000 | I5: =SUM(D5:H5) -> 300000
A6: سعر البيع عند موقع التجميع | B6: ر.ع / طن | D6: =SalePrice*F_Price*(1+PriceG)^(D$4-1) -> 38.66 | E6: =SalePrice*F_Price*(1+PriceG)^(E$4-1) -> 38.66 | F6: =SalePrice*F_Price*(1+PriceG)^(F$4-1) -> 38.66 | G6: =SalePrice*F_Price*(1+PriceG)^(G$4-1) -> 38.66 | H6: =SalePrice*F_Price*(1+PriceG)^(H$4-1) -> 38.66
A7: إجمالي الإيرادات | B7: ر.ع | D7: =D5*D6 -> 2319600 | E7: =E5*E6 -> 2319600 | F7: =F5*F6 -> 2319600 | G7: =G5*G6 -> 2319600 | H7: =H5*H6 -> 2319600 | I7: =SUM(D7:H7) -> 11598000

Sheet التكاليف التشغيلية
A1: التكاليف التشغيلية السنوية
A2: الثابتة لا تتغير مع الإنتاج؛ المتغيرة تتناسب مع نسبة استغلال الطاقة وأعباء تتبع العروق أو مع الإيرادات
A4: البند | B4: الوحدة | C4: 0 | D4: 1 | E4: 2 | F4: 3 | G4: 4 | H4: 5 | I4: الإجمالي
A5: معامل التضخم | B5: معامل | D5: =(1+InflRate)^(D$4-1) -> 1 | E5: =(1+InflRate)^(E$4-1) -> 1.015 | F5: =(1+InflRate)^(F$4-1) -> 1.030225 | G5: =(1+InflRate)^(G$4-1) -> 1.0456784 | H5: =(1+InflRate)^(H$4-1) -> 1.0613636
A6: نسبة استغلال الطاقة الإنتاجية | B6: % | D6: ='الخطة الفنية والإنتاج'!D20 -> 1 | E6: ='الخطة الفنية والإنتاج'!E20 -> 1 | F6: ='الخطة الفنية والإنتاج'!F20 -> 1 | G6: ='الخطة الفنية والإنتاج'!G20 -> 1 | H6: ='الخطة الفنية والإنتاج'!H20 -> 1
A7: نسبة الأعباء الإضافية لتتبع العروق | B7: % | D7: ='الخطة الفنية والإنتاج'!D21 -> 0 | E7: ='الخطة الفنية والإنتاج'!E21 -> 0.1 | F7: ='الخطة الفنية والإنتاج'!F21 -> 0.2 | G7: ='الخطة الفنية والإنتاج'!G21 -> 0.3 | H7: ='الخطة الفنية والإنتاج'!H21 -> 0.4
A8: أولاً: التكاليف الثابتة
A9: الأجور والرواتب | B9: ر.ع | D9: =Payroll*D$5*F_Opex -> 80040 | E9: =Payroll*E$5*F_Opex -> 81240.6 | F9: =Payroll*F$5*F_Opex -> 82459.209 | G9: =Payroll*G$5*F_Opex -> 83696.097 | H9: =Payroll*H$5*F_Opex -> 84951.539 | I9: =SUM(D9:H9) -> 412387.44
A10: التأمينات واشتراكات العمالة | B10: ر.ع | D10: =StaffOnCost*D$5*F_Opex -> 14379.8 | E10: =StaffOnCost*E$5*F_Opex -> 14595.497 | F10: =StaffOnCost*F$5*F_Opex -> 14814.429 | G10: =StaffOnCost*G$5*F_Opex -> 15036.646 | H10: =StaffOnCost*H$5*F_Opex -> 15262.196 | I10: =SUM(D10:H10) -> 74088.568
A11: إيجار المواقع | B11: ر.ع | D11: =SiteRent*D$5*F_Opex -> 10200 | E11: =SiteRent*E$5*F_Opex -> 10353 | F11: =SiteRent*F$5*F_Opex -> 10508.295 | G11: =SiteRent*G$5*F_Opex -> 10665.919 | H11: =SiteRent*H$5*F_Opex -> 10825.908 | I11: =SUM(D11:H11) -> 52553.123
A12: إيجار المعدات الشهري (المولد) | B12: ر.ع | D12: =EquipRent*D$5*F_Opex -> 480 | E12: =EquipRent*E$5*F_Opex -> 487.2 | F12: =EquipRent*F$5*F_Opex -> 494.508 | G12: =EquipRent*G$5*F_Opex -> 501.92562 | H12: =EquipRent*H$5*F_Opex -> 509.4545 | I12: =SUM(D12:H12) -> 2473.0881
A13: المواد المستهلكة — الجزء الثابت | B13: ر.ع | D13: =ConsFix*D$5*F_Opex -> 11296.32 | E13: =ConsFix*E$5*F_Opex -> 11465.765 | F13: =ConsFix*F$5*F_Opex -> 11637.751 | G13: =ConsFix*G$5*F_Opex -> 11812.318 | H13: =ConsFix*H$5*F_Opex -> 11989.502 | I13: =SUM(D13:H13) -> 58201.656
A14: نسبة الصيانة من تكلفة المعدات المملوكة | B14: % | D14: 0.04 | E14: 0.04 | F14: 0.05 | G14: 0.06 | H14: 0.06
A15: صيانة المعدات المملوكة | B15: ر.ع | D15: =MobileEq*D14*D$5*F_Opex -> 3720 | E15: =MobileEq*E14*E$5*F_Opex -> 3775.8 | F15: =MobileEq*F14*F$5*F_Opex -> 4790.5463 | G15: =MobileEq*G14*G$5*F_Opex -> 5834.8853 | H15: =MobileEq*H14*H$5*F_Opex -> 5922.4086 | I15: =SUM(D15:H15) -> 24043.64
A16: تأمين المعدات المملوكة | B16: ر.ع | D16: =MobileEq*EqIns*F_Opex -> 1395 | E16: =MobileEq*EqIns*F_Opex -> 1395 | F16: =MobileEq*EqIns*F_Opex -> 1395 | G16: =MobileEq*EqIns*F_Opex -> 1395 | H16: =MobileEq*EqIns*F_Opex -> 1395 | I16: =SUM(D16:H16) -> 6975
A17: تجديد التراخيص والرسوم الحكومية | B17: ر.ع | D17: =LicRenew*D$5*F_Opex -> 1600 | E17: =LicRenew*E$5*F_Opex -> 1624 | F17: =LicRenew*F$5*F_Opex -> 1648.36 | G17: =LicRenew*G$5*F_Opex -> 1673.0854 | H17: =LicRenew*H$5*F_Opex -> 1698.1817 | I17: =SUM(D17:H17) -> 8243.6271
A18: تجديد مأذونيات العمل (كل سنتين) | B18: ر.ع | D18: =IF(MOD(D$4,2)=0,PermitRenew,0)*F_Opex -> 0 | E18: =IF(MOD(E$4,2)=0,PermitRenew,0)*F_Opex -> 1708 | F18: =IF(MOD(F$4,2)=0,PermitRenew,0)*F_Opex -> 0 | G18: =IF(MOD(G$4,2)=0,PermitRenew,0)*F_Opex -> 1708 | H18: =IF(MOD(H$4,2)=0,PermitRenew,0)*F_Opex -> 0 | I18: =SUM(D18:H18) -> 3416
A19: مصاريف إدارية وعمومية | B19: ر.ع | D19: =GenAdmin*D$5*F_Opex -> 4800 | E19: =GenAdmin*E$5*F_Opex -> 4872 | F19: =GenAdmin*F$5*F_Opex -> 4945.08 | G19: =GenAdmin*G$5*F_Opex -> 5019.2562 | H19: =GenAdmin*H$5*F_Opex -> 5094.545 | I19: =SUM(D19:H19) -> 24730.881
A20: المنافع العامة | B20: ر.ع | D20: =Utilities*D$5*F_Opex -> 1800 | E20: =Utilities*E$5*F_Opex -> 1827 | F20: =Utilities*F$5*F_Opex -> 1854.405 | G20: =Utilities*G$5*F_Opex -> 1882.2211 | H20: =Utilities*H$5*F_Opex -> 1910.4544 | I20: =SUM(D20:H20) -> 9274.0805
A21: الفحص المخبري والتسويق | B21: ر.ع | D21: =AssayCost*D$5*F_Opex -> 2400 | E21: =AssayCost*E$5*F_Opex -> 2436 | F21: =AssayCost*F$5*F_Opex -> 2472.54 | G21: =AssayCost*G$5*F_Opex -> 2509.6281 | H21: =AssayCost*H$5*F_Opex -> 2547.2725 | I21: =SUM(D21:H21) -> 12365.441
A22: عمولة الضمان البنكي | B22: ر.ع | D22: =BankGuar*GuarComm*F_Opex -> 825 | E22: =BankGuar*GuarComm*F_Opex -> 825 | F22: =BankGuar*GuarComm*F_Opex -> 825 | G22: =BankGuar*GuarComm*F_Opex -> 825 | H22: =BankGuar*GuarComm*F_Opex -> 825 | I22: =SUM(D22:H22) -> 4125
A23: إعادة تأهيل الموقع | B23: ر.ع | D23: =RehabCost*D$5*F_Opex -> 2500 | E23: =RehabCost*E$5*F_Opex -> 2537.5 | F23: =RehabCost*F$5*F_Opex -> 2575.5625 | G23: =RehabCost*G$5*F_Opex -> 2614.1959 | H23: =RehabCost*H$5*F_Opex -> 2653.4089 | I23: =SUM(D23:H23) -> 12880.667
A24: إجمالي التكاليف الثابتة | B24: ر.ع | D24: =SUM(D9:D13)+SUM(D15:D23) -> 135436.12 | E24: =SUM(E9:E13)+SUM(E15:E23) -> 139142.36 | F24: =SUM(F9:F13)+SUM(F15:F23) -> 140420.69 | G24: =SUM(G9:G13)+SUM(G15:G23) -> 145174.18 | H24: =SUM(H9:H13)+SUM(H15:H23) -> 145584.87 | I24: =SUM(D24:H24) -> 705758.22
A25: ثانياً: التكاليف المتغيرة
A26: إيجار الحفارات بالساعة (شامل المشغل والديزل) | B26: ر.ع | D26: ='الخطة الفنية والإنتاج'!D25*HireRate*D$5*F_Opex -> 187200 | E26: ='الخطة الفنية والإنتاج'!E25*HireRate*E$5*F_Opex -> 209008.8 | F26: ='الخطة الفنية والإنتاج'!F25*HireRate*F$5*F_Opex -> 231429.74 | G26: ='الخطة الفنية والإنتاج'!G25*HireRate*G$5*F_Opex -> 254476.29 | H26: ='الخطة الفنية والإنتاج'!H25*HireRate*H$5*F_Opex -> 278162.16 | I26: =SUM(D26:H26) -> 1160277
A27: المواد المستهلكة — الجزء المتغير | B27: ر.ع | D27: =ConsVar*D6*(1+D7)*D$5*F_Opex -> 21306.024 | E27: =ConsVar*E6*(1+E7)*E$5*F_Opex -> 23788.176 | F27: =ConsVar*F6*(1+F7)*F$5*F_Opex -> 26339.998 | G27: =ConsVar*G6*(1+G7)*G$5*F_Opex -> 28963.023 | H27: =ConsVar*H6*(1+H7)*H$5*F_Opex -> 31658.812 | I27: =SUM(D27:H27) -> 132056.03
A28: الإتاوة الحكومية | B28: ر.ع | D28: =الإيرادات!D7*RoyaltyRate -> 115980 | E28: =الإيرادات!E7*RoyaltyRate -> 115980 | F28: =الإيرادات!F7*RoyaltyRate -> 115980 | G28: =الإيرادات!G7*RoyaltyRate -> 115980 | H28: =الإيرادات!H7*RoyaltyRate -> 115980 | I28: =SUM(D28:H28) -> 579900
A29: مساهمة تنمية المجتمع المحلي | B29: ر.ع | D29: =الإيرادات!D7*CommunityRate -> 23196 | E29: =الإيرادات!E7*CommunityRate -> 23196 | F29: =الإيرادات!F7*CommunityRate -> 23196 | G29: =الإيرادات!G7*CommunityRate -> 23196 | H29: =الإيرادات!H7*CommunityRate -> 23196 | I29: =SUM(D29:H29) -> 115980
A30: إجمالي التكاليف المتغيرة | B30: ر.ع | D30: =SUM(D26:D29) -> 347682.02 | E30: =SUM(E26:E29) -> 371972.98 | F30: =SUM(F26:F29) -> 396945.74 | G30: =SUM(G26:G29) -> 422615.31 | H30: =SUM(H26:H29) -> 448996.97 | I30: =SUM(D30:H30) -> 1988213
A31: إجمالي التكاليف التشغيلية النقدية | B31: ر.ع | D31: =D24+D30 -> 483118.14 | E31: =E24+E30 -> 511115.34 | F31: =F24+F30 -> 537366.43 | G31: =G24+G30 -> 567789.49 | H31: =H24+H30 -> 594581.84 | I31: =SUM(D31:H31) -> 2693971.2
A32: تكلفة الطن المباع | B32: ر.ع / طن | D32: =IF(الإيرادات!D5>0,D31/الإيرادات!D5,0) -> 8.0519691 | E32: =IF(الإيرادات!E5>0,E31/الإيرادات!E5,0) -> 8.518589 | F32: =IF(الإيرادات!F5>0,F31/الإيرادات!F5,0) -> 8.9561071 | G32: =IF(الإيرادات!G5>0,G31/الإيرادات!G5,0) -> 9.4631582 | H32: =IF(الإيرادات!H5>0,H31/الإيرادات!H5,0) -> 9.9096974 | I32: =IF(الإيرادات!I5>0,I31/الإيرادات!I5,0) -> 8.9799041

Sheet التكلفة الاستثمارية والتمويل
A1: التكلفة الاستثمارية ورأس المال العامل وهيكل التمويل
A2: تجمع كل ما يلزم إنفاقه قبل أول إيراد، مع بيان ما دُفع سابقاً وما يلزم تمويله
A4: البند | B4: القيمة (ر.ع) | C4: النسبة | D4: ملاحظات
A5: أولاً: التكلفة الاستثمارية الإجمالية
A6: الأصول الثابتة | B6: =FixedAssets -> 100500 | C6: =B6/$B$10 -> 0.19920416 | D6: من ورقة «الأصول والإهلاك»
A7: مصاريف ما قبل التشغيل (شاملة مصاريف الاستكشاف السابقة) | B7: =PreOp -> 228228 | C7: =B7/$B$10 -> 0.45237778 | D7: من ورقة «مصاريف ما قبل التشغيل»
A8: الضمانات البنكية (وديعة مستردة) | B8: =BankGuar -> 55000 | C8: =B8/$B$10 -> 0.1090172 | D8: تُسترد بعد إغلاق المحجر وإعادة تأهيله
A9: رأس المال العامل | B9: =B17 -> 120779.54 | C9: =B9/$B$10 -> 0.23940086 | D9: محتسب أدناه
A10: إجمالي التكلفة الاستثمارية | B10: =SUM(B6:B9) -> 504507.54 | C10: =SUM(C6:C9) -> 1
A11: منها: مصاريف مدفوعة سابقاً | B11: =SunkCost -> 200000 | C11: =B11/$B$10 -> 0.39642619 | D11: مساهمة المالك المنفذة
A12: الاستثمار الجديد المطلوب | B12: =B10-B11 -> 304507.54 | C12: =B12/$B$10 -> 0.60357381
A14: ثانياً: رأس المال العامل
A15: التكاليف التشغيلية النقدية للسنة الأولى | B15: ='التكاليف التشغيلية'!D31 -> 483118.14 | D15: من ورقة «التكاليف التشغيلية» (كان صفراً في الملف الأصلي بسبب الروابط المكسورة)
A16: عدد أشهر التغطية | B16: =WCMonths -> 3
A17: رأس المال العامل المطلوب | B17: =B15*B16/12 -> 120779.54
A19: ثالثاً: هيكل التمويل
A20: قرض بنكي | B20: =Loan -> 150000 | C20: =B20/$B$23 -> 0.29731964
A21: مساهمة المالك — مدفوعة سابقاً | B21: =SunkCost -> 200000 | C21: =B21/$B$23 -> 0.39642619
A22: مساهمة المالك — نقد جديد | B22: =B10-B20-B21 -> 154507.54 | C22: =B22/$B$23 -> 0.30625417
A23: إجمالي مصادر التمويل | B23: =SUM(B20:B22) -> 504507.54 | C23: =SUM(C20:C22) -> 1
A24: نسبة القرض إلى الاستثمار الجديد | B24: =IF(NewInv>0,Loan/NewInv,0) -> 0.49259865
A26: جدول سداد القرض | B26: الوحدة | C26: 0 | D26: 1 | E26: 2 | F26: 3 | G26: 4 | H26: 5 | I26: الإجمالي
A27: رصيد القرض أول السنة | B27: ر.ع | D27: =C31 -> 150000 | E27: =D31 -> 123390.54 | F27: =E31 -> 95184.512 | G27: =F31 -> 65286.123 | H27: =G31 -> 33593.83
A28: القسط السنوي (أصل + فائدة) | B28: ر.ع | D28: =IF(AND(D$26<=LoanYrs,Loan>0),-PMT(LoanRate,LoanYrs,Loan),0) -> 35609.46 | E28: =IF(AND(E$26<=LoanYrs,Loan>0),-PMT(LoanRate,LoanYrs,Loan),0) -> 35609.46 | F28: =IF(AND(F$26<=LoanYrs,Loan>0),-PMT(LoanRate,LoanYrs,Loan),0) -> 35609.46 | G28: =IF(AND(G$26<=LoanYrs,Loan>0),-PMT(LoanRate,LoanYrs,Loan),0) -> 35609.46 | H28: =IF(AND(H$26<=LoanYrs,Loan>0),-PMT(LoanRate,LoanYrs,Loan),0) -> 35609.46 | I28: =SUM(D28:H28) -> 178047.3
A29: الفائدة | B29: ر.ع | D29: =D27*LoanRate -> 9000 | E29: =E27*LoanRate -> 7403.4324 | F29: =F27*LoanRate -> 5711.0707 | G29: =G27*LoanRate -> 3917.1674 | H29: =H27*LoanRate -> 2015.6298 | I29: =SUM(D29:H29) -> 28047.3
A30: سداد أصل القرض | B30: ر.ع | D30: =D28-D29 -> 26609.46 | E30: =E28-E29 -> 28206.028 | F30: =F28-F29 -> 29898.389 | G30: =G28-G29 -> 31692.293 | H30: =H28-H29 -> 33593.83 | I30: =SUM(D30:H30) -> 150000
A31: رصيد القرض آخر السنة | B31: ر.ع | C31: =Loan -> 150000 | D31: =D27-D30 -> 123390.54 | E31: =E27-E30 -> 95184.512 | F31: =F27-F30 -> 65286.123 | G31: =G27-G30 -> 33593.83 | H31: =H27-H30 -> 0

Sheet قائمة الدخل
A1: قائمة الدخل التقديرية
A2: خمس سنوات تشغيل — بالريال العُماني
A4: البند | B4: الوحدة | C4: 0 | D4: 1 | E4: 2 | F4: 3 | G4: 4 | H4: 5 | I4: الإجمالي
A5: الإيرادات | B5: ر.ع | D5: =الإيرادات!D7 -> 2319600 | E5: =الإيرادات!E7 -> 2319600 | F5: =الإيرادات!F7 -> 2319600 | G5: =الإيرادات!G7 -> 2319600 | H5: =الإيرادات!H7 -> 2319600 | I5: =SUM(D5:H5) -> 11598000
A6: التكاليف الثابتة | B6: ر.ع | D6: ='التكاليف التشغيلية'!D24 -> 135436.12 | E6: ='التكاليف التشغيلية'!E24 -> 139142.36 | F6: ='التكاليف التشغيلية'!F24 -> 140420.69 | G6: ='التكاليف التشغيلية'!G24 -> 145174.18 | H6: ='التكاليف التشغيلية'!H24 -> 145584.87 | I6: =SUM(D6:H6) -> 705758.22
A7: التكاليف المتغيرة (إيجار الحفارات والمواد المستهلكة) | B7: ر.ع | D7: ='التكاليف التشغيلية'!D26+'التكاليف التشغيلية'!D27 -> 208506.02 | E7: ='التكاليف التشغيلية'!E26+'التكاليف التشغيلية'!E27 -> 232796.98 | F7: ='التكاليف التشغيلية'!F26+'التكاليف التشغيلية'!F27 -> 257769.74 | G7: ='التكاليف التشغيلية'!G26+'التكاليف التشغيلية'!G27 -> 283439.31 | H7: ='التكاليف التشغيلية'!H26+'التكاليف التشغيلية'!H27 -> 309820.97 | I7: =SUM(D7:H7) -> 1292333
A8: الإتاوة ومساهمة تنمية المجتمع | B8: ر.ع | D8: ='التكاليف التشغيلية'!D28+'التكاليف التشغيلية'!D29 -> 139176 | E8: ='التكاليف التشغيلية'!E28+'التكاليف التشغيلية'!E29 -> 139176 | F8: ='التكاليف التشغيلية'!F28+'التكاليف التشغيلية'!F29 -> 139176 | G8: ='التكاليف التشغيلية'!G28+'التكاليف التشغيلية'!G29 -> 139176 | H8: ='التكاليف التشغيلية'!H28+'التكاليف التشغيلية'!H29 -> 139176 | I8: =SUM(D8:H8) -> 695880
A9: إجمالي التكاليف التشغيلية | B9: ر.ع | D9: =SUM(D6:D8) -> 483118.14 | E9: =SUM(E6:E8) -> 511115.34 | F9: =SUM(F6:F8) -> 537366.43 | G9: =SUM(G6:G8) -> 567789.49 | H9: =SUM(H6:H8) -> 594581.84 | I9: =SUM(D9:H9) -> 2693971.2
A10: الربح قبل الفوائد والضرائب والإهلاك (EBITDA) | B10: ر.ع | D10: =D5-D9 -> 1836481.9 | E10: =E5-E9 -> 1808484.7 | F10: =F5-F9 -> 1782233.6 | G10: =G5-G9 -> 1751810.5 | H10: =H5-H9 -> 1725018.2 | I10: =SUM(D10:H10) -> 8904028.8
A11: الإهلاك | B11: ر.ع | D11: ='الأصول والإهلاك'!D19 -> 13217.143 | E11: ='الأصول والإهلاك'!E19 -> 13217.143 | F11: ='الأصول والإهلاك'!F19 -> 13217.143 | G11: ='الأصول والإهلاك'!G19 -> 13217.143 | H11: ='الأصول والإهلاك'!H19 -> 13217.143 | I11: =SUM(D11:H11) -> 66085.714
A12: إطفاء مصاريف ما قبل التشغيل | B12: ر.ع | D12: =IF(D$4<=AmortYrs,PreOp/AmortYrs,0) -> 45645.6 | E12: =IF(E$4<=AmortYrs,PreOp/AmortYrs,0) -> 45645.6 | F12: =IF(F$4<=AmortYrs,PreOp/AmortYrs,0) -> 45645.6 | G12: =IF(G$4<=AmortYrs,PreOp/AmortYrs,0) -> 45645.6 | H12: =IF(H$4<=AmortYrs,PreOp/AmortYrs,0) -> 45645.6 | I12: =SUM(D12:H12) -> 228228
A13: الربح التشغيلي (EBIT) | B13: ر.ع | D13: =D10-D11-D12 -> 1777619.1 | E13: =E10-E11-E12 -> 1749621.9 | F13: =F10-F11-F12 -> 1723370.8 | G13: =G10-G11-G12 -> 1692947.8 | H13: =H10-H11-H12 -> 1666155.4 | I13: =SUM(D13:H13) -> 8609715
A14: فوائد القرض | B14: ر.ع | D14: ='التكلفة الاستثمارية والتمويل'!D29 -> 9000 | E14: ='التكلفة الاستثمارية والتمويل'!E29 -> 7403.4324 | F14: ='التكلفة الاستثمارية والتمويل'!F29 -> 5711.0707 | G14: ='التكلفة الاستثمارية والتمويل'!G29 -> 3917.1674 | H14: ='التكلفة الاستثمارية والتمويل'!H29 -> 2015.6298 | I14: =SUM(D14:H14) -> 28047.3
A15: الربح قبل الضريبة | B15: ر.ع | D15: =D13-D14 -> 1768619.1 | E15: =E13-E14 -> 1742218.5 | F15: =F13-F14 -> 1717659.8 | G15: =G13-G14 -> 1689030.6 | H15: =H13-H14 -> 1664139.8 | I15: =SUM(D15:H15) -> 8581667.7
A16: خسائر ضريبية مرحّلة أول السنة | B16: ر.ع | D16: =C17 -> 0 | E16: =D17 -> 0 | F16: =E17 -> 0 | G16: =F17 -> 0 | H16: =G17 -> 0
A17: خسائر ضريبية مرحّلة آخر السنة | B17: ر.ع | C17: 0 | D17: =MAX(0,D16-D15) -> 0 | E17: =MAX(0,E16-E15) -> 0 | F17: =MAX(0,F16-F15) -> 0 | G17: =MAX(0,G16-G15) -> 0 | H17: =MAX(0,H16-H15) -> 0
A18: الوعاء الضريبي | B18: ر.ع | D18: =MAX(0,D15-D16) -> 1768619.1 | E18: =MAX(0,E15-E16) -> 1742218.5 | F18: =MAX(0,F15-F16) -> 1717659.8 | G18: =MAX(0,G15-G16) -> 1689030.6 | H18: =MAX(0,H15-H16) -> 1664139.8 | I18: =SUM(D18:H18) -> 8581667.7
A19: ضريبة الدخل | B19: ر.ع | D19: =D18*TaxRate -> 265292.87 | E19: =E18*TaxRate -> 261332.77 | F19: =F18*TaxRate -> 257648.96 | G19: =G18*TaxRate -> 253354.59 | H19: =H18*TaxRate -> 249620.97 | I19: =SUM(D19:H19) -> 1287250.2
A20: صافي الربح بعد الضريبة | B20: ر.ع | D20: =D15-D19 -> 1503326.2 | E20: =E15-E19 -> 1480885.7 | F20: =F15-F19 -> 1460010.8 | G20: =G15-G19 -> 1435676 | H20: =H15-H19 -> 1414518.8 | I20: =SUM(D20:H20) -> 7294417.6
A21: هامش EBITDA | B21: % | D21: =IF(D5>0,D10/D5,0) -> 0.79172351 | E21: =IF(E5>0,E10/E5,0) -> 0.77965367 | F21: =IF(F5>0,F10/F5,0) -> 0.7683366 | G21: =IF(G5>0,G10/G5,0) -> 0.75522095 | H21: =IF(H5>0,H10/H5,0) -> 0.74367053 | I21: =IF(I5>0,I10/I5,0) -> 0.76772105
A22: هامش صافي الربح | B22: % | D22: =IF(D5>0,D20/D5,0) -> 0.64809719 | E22: =IF(E5>0,E20/E5,0) -> 0.63842288 | F22: =IF(F5>0,F20/F5,0) -> 0.62942352 | G22: =IF(G5>0,G20/G5,0) -> 0.61893258 | H22: =IF(H5>0,H20/H5,0) -> 0.60981153 | I22: =IF(I5>0,I20/I5,0) -> 0.62893754
A23: ملاحظة: احتُسبت الضريبة على الربح المحاسبي (إهلاك القسط الثابت). الإهلاك الضريبي الفعلي للمعدات الثقيلة (33.33% رصيد متناقص) يؤجل جزءاً من الضريبة في السنوات الأولى.

Sheet التدفقات النقدية
A1: قائمة التدفقات النقدية التقديرية
A2: التدفقات الداخلة موجبة والخارجة سالبة — سنة التأسيس (0) ثم عشر سنوات تشغيل
A4: البند | B4: الوحدة | C4: 0 | D4: 1 | E4: 2 | F4: 3 | G4: 4 | H4: 5 | I4: الإجمالي
A5: أولاً: التدفقات النقدية للمشروع (قبل التمويل)
A6: الإيرادات | B6: ر.ع | C6: 0 | D6: =الإيرادات!D7 -> 2319600 | E6: =الإيرادات!E7 -> 2319600 | F6: =الإيرادات!F7 -> 2319600 | G6: =الإيرادات!G7 -> 2319600 | H6: =الإيرادات!H7 -> 2319600 | I6: =SUM(C6:H6) -> 11598000
A7: التكاليف التشغيلية النقدية | B7: ر.ع | C7: 0 | D7: =-'التكاليف التشغيلية'!D31 -> -483118.14 | E7: =-'التكاليف التشغيلية'!E31 -> -511115.34 | F7: =-'التكاليف التشغيلية'!F31 -> -537366.43 | G7: =-'التكاليف التشغيلية'!G31 -> -567789.49 | H7: =-'التكاليف التشغيلية'!H31 -> -594581.84 | I7: =SUM(C7:H7) -> -2693971.2
A8: ضريبة الدخل | B8: ر.ع | C8: 0 | D8: =-'قائمة الدخل'!D19 -> -265292.87 | E8: =-'قائمة الدخل'!E19 -> -261332.77 | F8: =-'قائمة الدخل'!F19 -> -257648.96 | G8: =-'قائمة الدخل'!G19 -> -253354.59 | H8: =-'قائمة الدخل'!H19 -> -249620.97 | I8: =SUM(C8:H8) -> -1287250.2
A9: الأصول الثابتة واستبدالها | B9: ر.ع | C9: =-FixedAssets -> -100500 | D9: =-'الأصول والإهلاك'!D20 -> 0 | E9: =-'الأصول والإهلاك'!E20 -> 0 | F9: =-'الأصول والإهلاك'!F20 -> 0 | G9: =-'الأصول والإهلاك'!G20 -> 0 | H9: =-'الأصول والإهلاك'!H20 -> 0 | I9: =SUM(C9:H9) -> -100500
A10: مصاريف ما قبل التشغيل | B10: ر.ع | C10: =-PreOp -> -228228 | D10: 0 | E10: 0 | F10: 0 | G10: 0 | H10: 0 | I10: =SUM(C10:H10) -> -228228
A11: الضمانات البنكية (إيداع / استرداد) | B11: ر.ع | C11: =-BankGuar -> -55000 | D11: 0 | E11: 0 | F11: 0 | G11: 0 | H11: =BankGuar -> 55000 | I11: =SUM(C11:H11) -> 0
A12: رأس المال العامل (تكوين / استرداد) | B12: ر.ع | C12: =-WorkCap -> -120779.54 | D12: 0 | E12: 0 | F12: 0 | G12: 0 | H12: =WorkCap -> 120779.54 | I12: =SUM(C12:H12) -> 0
A13: القيمة التخريدية للأصول (صافي القيمة الدفترية) | B13: ر.ع | C13: 0 | D13: 0 | E13: 0 | F13: 0 | G13: 0 | H13: ='الأصول والإهلاك'!H23 -> 34414.286 | I13: =SUM(C13:H13) -> 34414.286
A14: صافي التدفق النقدي للمشروع | B14: ر.ع | C14: =SUM(C6:C13) -> -504507.54 | D14: =SUM(D6:D13) -> 1571189 | E14: =SUM(E6:E13) -> 1547151.9 | F14: =SUM(F6:F13) -> 1524584.6 | G14: =SUM(G6:G13) -> 1498455.9 | H14: =SUM(H6:H13) -> 1685591 | I14: =SUM(C14:H14) -> 7322464.9
A15: التدفق النقدي التراكمي | B15: ر.ع | C15: =C14 -> -504507.54 | D15: =C15+D14 -> 1066681.5 | E15: =D15+E14 -> 2613833.3 | F15: =E15+F14 -> 4138417.9 | G15: =F15+G14 -> 5636873.9 | H15: =G15+H14 -> 7322464.9
A16: معامل الخصم | B16: معامل | C16: =1/(1+DiscRate)^C$4 -> 1 | D16: =1/(1+DiscRate)^D$4 -> 0.89285714 | E16: =1/(1+DiscRate)^E$4 -> 0.79719388 | F16: =1/(1+DiscRate)^F$4 -> 0.71178025 | G16: =1/(1+DiscRate)^G$4 -> 0.63551808 | H16: =1/(1+DiscRate)^H$4 -> 0.56742686
A17: التدفق النقدي المخصوم | B17: ر.ع | C17: =C14*C16 -> -504507.54 | D17: =D14*D16 -> 1402847.3 | E17: =E14*E16 -> 1233380 | F17: =F14*F16 -> 1085169.2 | G17: =G14*G16 -> 952295.83 | H17: =H14*H16 -> 956449.61 | I17: =SUM(C17:H17) -> 5125634.4
A18: التدفق المخصوم التراكمي | B18: ر.ع | C18: =C17 -> -504507.54 | D18: =C18+D17 -> 898339.78 | E18: =D18+E17 -> 2131719.8 | F18: =E18+F17 -> 3216889 | G18: =F18+G17 -> 4169184.8 | H18: =G18+H17 -> 5125634.4
A19: ثانياً: التدفقات باستبعاد المصاريف المدفوعة سابقاً (الاستثمار الجديد فقط)
A20: صافي التدفق النقدي — الاستثمار الجديد | B20: ر.ع | C20: =C14+SunkCost -> -304507.54 | D20: =D14 -> 1571189 | E20: =E14 -> 1547151.9 | F20: =F14 -> 1524584.6 | G20: =G14 -> 1498455.9 | H20: =H14 -> 1685591 | I20: =SUM(C20:H20) -> 7522464.9
A21: ثالثاً: التمويل والتدفقات للمالك
A22: سحب القرض | B22: ر.ع | C22: =Loan -> 150000 | D22: 0 | E22: 0 | F22: 0 | G22: 0 | H22: 0 | I22: =SUM(C22:H22) -> 150000
A23: سداد أصل القرض | B23: ر.ع | C23: 0 | D23: =-'التكلفة الاستثمارية والتمويل'!D30 -> -26609.46 | E23: =-'التكلفة الاستثمارية والتمويل'!E30 -> -28206.028 | F23: =-'التكلفة الاستثمارية والتمويل'!F30 -> -29898.389 | G23: =-'التكلفة الاستثمارية والتمويل'!G30 -> -31692.293 | H23: =-'التكلفة الاستثمارية والتمويل'!H30 -> -33593.83 | I23: =SUM(C23:H23) -> -150000
A24: فوائد القرض | B24: ر.ع | C24: 0 | D24: =-'التكلفة الاستثمارية والتمويل'!D29 -> -9000 | E24: =-'التكلفة الاستثمارية والتمويل'!E29 -> -7403.4324 | F24: =-'التكلفة الاستثمارية والتمويل'!F29 -> -5711.0707 | G24: =-'التكلفة الاستثمارية والتمويل'!G29 -> -3917.1674 | H24: =-'التكلفة الاستثمارية والتمويل'!H29 -> -2015.6298 | I24: =SUM(C24:H24) -> -28047.3
A25: صافي التدفق النقدي للمالك | B25: ر.ع | C25: =C14+C22+C23+C24 -> -354507.54 | D25: =D14+D22+D23+D24 -> 1535579.5 | E25: =E14+E22+E23+E24 -> 1511542.4 | F25: =F14+F22+F23+F24 -> 1488975.1 | G25: =G14+G22+G23+G24 -> 1462846.5 | H25: =H14+H22+H23+H24 -> 1649981.6 | I25: =SUM(C25:H25) -> 7294417.6
A26: الرصيد النقدي التراكمي للمالك | B26: ر.ع | C26: =C25 -> -354507.54 | D26: =C26+D25 -> 1181072 | E26: =D26+E25 -> 2692614.4 | F26: =E26+F25 -> 4181589.6 | G26: =F26+G25 -> 5644436 | H26: =G26+H25 -> 7294417.6
A27: معدل تغطية خدمة الدين (DSCR) | B27: مرة | D27: =IF('التكلفة الاستثمارية والتمويل'!D28>0,('قائمة الدخل'!D10-'قائمة الدخل'!D19)/'التكلفة الاستثمارية والتمويل'!D28,"") -> 44.122797 | E27: =IF('التكلفة الاستثمارية والتمويل'!E28>0,('قائمة الدخل'!E10-'قائمة الدخل'!E19)/'التكلفة الاستثمارية والتمويل'!E28,"") -> 43.447777 | F27: =IF('التكلفة الاستثمارية والتمويل'!F28>0,('قائمة الدخل'!F10-'قائمة الدخل'!F19)/'التكلفة الاستثمارية والتمويل'!F28,"") -> 42.814033 | G27: =IF('التكلفة الاستثمارية والتمويل'!G28>0,('قائمة الدخل'!G10-'قائمة الدخل'!G19)/'التكلفة الاستثمارية والتمويل'!G28,"") -> 42.080276 | H27: =IF('التكلفة الاستثمارية والتمويل'!H28>0,('قائمة الدخل'!H10-'قائمة الدخل'!H19)/'التكلفة الاستثمارية والتمويل'!H28,"") -> 41.432731

Sheet المؤشرات المالية
A1: مؤشرات الجدوى المالية
A2: محتسبة من قائمة التدفقات النقدية وقائمة الدخل
A4: المؤشر | B4: القيمة | C4: الوحدة | D4: التفسير
A5: أولاً: على إجمالي الاستثمار (شاملاً المصاريف المدفوعة سابقاً)
A6: صافي القيمة الحالية (NPV) | B6: ='التدفقات النقدية'!C14+NPV(DiscRate,'التدفقات النقدية'!D14:H14) -> 5125634.4 | C6: ر.ع | D6: موجب = المشروع يحقق عائداً أعلى من معدل الخصم
A7: معدل العائد الداخلي (IRR) | B7: =IFERROR(IRR('التدفقات النقدية'!C14:H14),"غير محدد") -> 3.097682 | C7: % | D7: يُقارن بمعدل الخصم وبتكلفة التمويل
A8: فترة الاسترداد | B8: =IFERROR(IF('التدفقات النقدية'!H15<0,"لا يُسترد خلال مدة الدراسة",COUNTIF('التدفقات النقدية'!C15:H15,"<0")-1+(-INDEX('التدفقات النقدية'!C15:H15,COUNTIF('التدفقات النقدية'!C15:H15,"<0")))/INDEX('التدفقات النقدية'!C14:H14,COUNTIF('التدفقات النقدية'!C15:H15,"<0")+1)),"غير محدد") -> 0.32109921 | C8: سنة | D8: من بداية الإنتاج حتى استرداد كامل الاستثمار (غير مخصومة)
A9: فترة الاسترداد المخصومة | B9: =IFERROR(IF('التدفقات النقدية'!H18<0,"لا يُسترد خلال مدة الدراسة",COUNTIF('التدفقات النقدية'!C18:H18,"<0")-1+(-INDEX('التدفقات النقدية'!C18:H18,COUNTIF('التدفقات النقدية'!C18:H18,"<0")))/INDEX('التدفقات النقدية'!C17:H17,COUNTIF('التدفقات النقدية'!C18:H18,"<0")+1)),"غير محدد") -> 0.35963111 | C9: سنة | D9: بعد خصم التدفقات بمعدل الخصم
A10: مؤشر الربحية (PI) | B10: =IF('التدفقات النقدية'!C14<0,(B6-'التدفقات النقدية'!C14)/(-'التدفقات النقدية'!C14),0) -> 11.159679 | C10: مرة | D10: القيمة الحالية للتدفقات ÷ الاستثمار — أكبر من 1 = مجدٍ
A11: ثانياً: على الاستثمار الجديد فقط (باستبعاد المصاريف المدفوعة سابقاً)
A12: صافي القيمة الحالية | B12: ='التدفقات النقدية'!C20+NPV(DiscRate,'التدفقات النقدية'!D20:H20) -> 5325634.4 | C12: ر.ع | D12: المعيار الصحيح لقرار المضي في المشروع: المصاريف السابقة لا تُسترد سواء نُفّذ المشروع أم لا
A13: معدل العائد الداخلي | B13: =IFERROR(IRR('التدفقات النقدية'!C20:H20),"غير محدد") -> 5.1443895 | C13: %
A14: ثالثاً: للمالك وللممول
A15: معدل العائد الداخلي على حقوق الملكية | B15: =IFERROR(IRR('التدفقات النقدية'!C25:H25),"غير محدد") -> 4.3156503 | C15: % | D15: بعد سحب القرض وسداده
A16: أدنى معدل تغطية لخدمة الدين (DSCR) | B16: =IF(Loan>0,MIN('التدفقات النقدية'!D27:H27),"لا يوجد قرض") -> 41.432731 | C16: مرة | D16: البنوك تشترط عادة 1.25 فأكثر
A17: أدنى رصيد نقدي تراكمي للمالك بعد سنة التأسيس | B17: =MIN('التدفقات النقدية'!D26:H26) -> 1181072 | C17: ر.ع
A18: رابعاً: الربحية
A19: متوسط صافي الربح السنوي | B19: =AVERAGE('قائمة الدخل'!D20:H20) -> 1458883.5 | C19: ر.ع
A20: متوسط العائد على إجمالي الاستثمار (ROI) | B20: =B19/TotalInv -> 2.8916982 | C20: %
A21: متوسط هامش EBITDA | B21: ='قائمة الدخل'!I21 -> 0.76772105 | C21: % | D21: للمقارنة: شركة تنمية معادن عُمان تستهدف هامشاً يفوق 20% من إنتاج الكروم
A22: متوسط تكلفة الطن المباع | B22: ='التكاليف التشغيلية'!I32 -> 8.9799041 | C22: ر.ع / طن
A23: خامساً: نقطة التعادل — السنة الثالثة (الطاقة الكاملة)
A24: الكمية المباعة | B24: =الإيرادات!F5 -> 60000 | C24: طن
A25: التكاليف الثابتة شاملة الإهلاك والإطفاء والفوائد | B25: ='التكاليف التشغيلية'!F24+'قائمة الدخل'!F11+'قائمة الدخل'!F12+'قائمة الدخل'!F14 -> 204994.5 | C25: ر.ع
A26: التكلفة المتغيرة للطن (إيجار الحفارات والمواد المستهلكة) | B26: =IF(B24>0,('التكاليف التشغيلية'!F26+'التكاليف التشغيلية'!F27)/B24,0) -> 4.2961624 | C26: ر.ع / طن
A27: صافي سعر الطن بعد الإتاوة والمساهمة المجتمعية | B27: =الإيرادات!F6*(1-RoyaltyRate-CommunityRate) -> 36.3404 | C27: ر.ع / طن
A28: نسبة التعادل من الطاقة الإنتاجية | B28: =IF(B24>0,(B25/(B27-B26))/B24,0) -> 0.10662057 | C28: % | D28: كلما انخفضت زاد هامش الأمان
A29: سعر التعادل | B29: =IF(B24>0,(B25+'التكاليف التشغيلية'!F26+'التكاليف التشغيلية'!F27)/(B24*(1-RoyaltyRate-CommunityRate)),0) -> 8.2050398 | C29: ر.ع / طن | D29: يُقارن بسعر البيع المعتمد وبمتوسط السعر الوطني المحقق 2025
A30: كمية التعادل | B30: =B28*B24 -> 6397.2344 | C30: طن
A31: هامش الأمان | B31: =1-B28 -> 0.89337943 | C31: % | D31: نسبة الانخفاض في المبيعات التي يتحملها المشروع قبل تحقيق خسارة

Sheet تحليل الحساسية
A1: تحليل الحساسية
A2: يوضح أثر تغير أهم العوامل على صافي القيمة الحالية ومعدل العائد الداخلي. الجداول تُحتسب تلقائياً (جداول بيانات Excel) — لا تُعدَّل خلاياها
A4: عوامل الحساسية (تبقى 100% في الحالة الأساسية)
A5: معامل سعر البيع | B5: 1
A6: معامل الكمية المباعة | B6: 1
A7: معامل التكاليف التشغيلية | B7: 1
A8: معامل تكلفة الأصول الثابتة | B8: 1
A9: معامل الكمية يمثل تغير الخام القابل للبيع مع ثبات ساعات الحفر (أي تغير نسبة الاسترداد أو جودة العروق).
A11: 1) حساسية سعر البيع | G11: 5) صافي القيمة الحالية (ر.ع): سعر البيع × الكمية المباعة
A12: معامل السعر | B12: صافي القيمة الحالية (ر.ع) | C12: معدل العائد الداخلي | D12: العائد الداخلي على الاستثمار الجديد | G12: معامل السعر (عمودي) | H12: معامل الكمية المباعة (أفقي)
A13: الحالة الأساسية | B13: =K_NPV -> 5125634.4 | C13: =K_IRR -> 3.097682 | D13: =K_IRRNew -> 5.1443895 | G13: =K_NPV -> 5125634.4 | H13: 0.7 | I13: 0.8 | J13: 0.9 | K13: 1 | L13: 1.1 | M13: 1.2 | N13: 1.3
A14: 0.7 | B14: 3125864.9 | C14: 2.0271183 | D14: 0.074787374 | G14: 0.7 | H14: 1726026.2 | I14: 2192639.1 | J14: 2659252 | K14: 3125864.9 | L14: 3592477.8 | M14: 4059090.7 | N14: 4525703.6
A15: 0.8 | B15: 3792454.7 | C15: 2.3901899 | D15: 0.20084901 | G15: 0.8 | H15: 2192639.1 | I15: 2725911 | J15: 3259182.9 | K15: 3792454.7 | L15: 4325726.6 | M15: 4858998.5 | N15: 5392270.4
A16: 0.9 | B16: 4459044.6 | C16: 2.7468284 | D16: 0.31047951 | G16: 0.9 | H16: 2659252 | I16: 3259182.9 | J16: 3859113.7 | K16: 4459044.6 | L16: 5058975.4 | M16: 5658906.3 | N16: 6258837.2
A17: 1 | B17: 5125634.4 | C17: 3.097682 | D17: 0.41139051 | G17: 1 | H17: 3125864.9 | I17: 3792454.7 | J17: 4459044.6 | K17: 5125634.4 | L17: 5792224.3 | M17: 6458814.1 | N17: 7125404
A18: 1.1 | B18: 5792224.3 | C18: 3.4431609 | D18: 0.50724292 | G18: 1.1 | H18: 3592477.8 | I18: 4325726.6 | J18: 5058975.4 | K18: 5792224.3 | L18: 6525473.1 | M18: 7258722 | N18: 7991970.8
A19: 1.2 | B19: 6458814.1 | C19: 3.7835493 | D19: 0.59977404 | G19: 1.2 | H19: 4059090.7 | I19: 4858998.5 | J19: 5658906.3 | K19: 6458814.1 | L19: 7258722 | M19: 8058629.8 | N19: 8858537.6
A20: 1.3 | B20: 7125404 | C20: 4.1190604 | D20: 0.68997541 | G20: 1.3 | H20: 4525703.6 | I20: 5392270.4 | J20: 6258837.2 | K20: 7125404 | L20: 7991970.8 | M20: 8858537.6 | N20: 9725104.4
A22: 2) حساسية الكمية المباعة | G22: قراءة النتائج
A23: معامل الكمية | B23: صافي القيمة الحالية (ر.ع) | C23: معدل العائد الداخلي | D23: العائد الداخلي على الاستثمار الجديد | G23: • الخلايا الحمراء = صافي قيمة حالية سالب (المشروع غير مجدٍ عند ذلك السيناريو).
A24: الحالة الأساسية | B24: =K_NPV -> 5125634.4 | C24: =K_IRR -> 3.097682 | D24: =K_IRRNew -> 5.1443895 | G24: • معامل السعر يُطبَّق على سعر البيع المعتمد (المرجّح بين البيع المحلي والتصدير).
A25: 0.7 | B25: 3125864.9 | C25: 2.0271183 | D25: 0.074787374 | G25: • معامل الكمية 85% يعادل تقريباً انخفاض نسبة الاسترداد بعد الفرز من 85% إلى 72%.
A26: 0.8 | B26: 3792454.7 | C26: 2.3901899 | D26: 0.20084901
A27: 0.9 | B27: 4459044.6 | C27: 2.7468284 | D27: 0.31047951
A28: 1 | B28: 5125634.4 | C28: 3.097682 | D28: 0.41139051
A29: 1.1 | B29: 5792224.3 | C29: 3.4431609 | D29: 0.50724292
A30: 1.2 | B30: 6458814.1 | C30: 3.7835493 | D30: 0.59977404
A31: 1.3 | B31: 7125404 | C31: 4.1190604 | D31: 0.68997541
A33: 3) حساسية التكاليف التشغيلية
A34: معامل التكاليف | B34: صافي القيمة الحالية (ر.ع) | C34: معدل العائد الداخلي | D34: العائد الداخلي على الاستثمار الجديد
A35: الحالة الأساسية | B35: =K_NPV -> 5125634.4 | C35: =K_IRR -> 3.097682 | D35: =K_IRRNew -> 5.1443895
A36: 0.7 | B36: 5498338.1 | C36: 3.4540749 | D36: 0.6202188
A37: 0.8 | B37: 5374103.5 | C37: 3.3312149 | D37: 0.54909511
A38: 0.9 | B38: 5249869 | C38: 3.21249 | D38: 0.47962718
A39: 1 | B39: 5125634.4 | C39: 3.097682 | D39: 0.41139051
A40: 1.1 | B40: 5001399.9 | C40: 2.9865866 | D40: 0.34386144
A41: 1.2 | B41: 4877165.3 | C41: 2.8790123 | D41: 0.27630589
A42: 1.3 | B42: 4752930.8 | C42: 2.7747799 | D42: 0.20757782
A44: 4) حساسية تكلفة الأصول الثابتة
A45: معامل تكلفة الأصول | B45: صافي القيمة الحالية (ر.ع) | C45: معدل العائد الداخلي | D45: العائد الداخلي على الاستثمار الجديد
A46: الحالة الأساسية | B46: =K_NPV -> 5125634.4 | C46: =K_IRR -> 3.097682 | D46: =K_IRRNew -> 5.1443895
A47: 0.7 | B47: 5153516.9 | C47: 3.3000893 | D47: 0.50278108
A48: 0.8 | B48: 5144222.8 | C48: 3.2297905 | D48: 0.46886742
A49: 0.9 | B49: 5134928.6 | C49: 3.1623798 | D49: 0.43860906
A50: 1 | B50: 5125634.4 | C50: 3.097682 | D50: 0.41139051
A51: 1.1 | B51: 5116340.3 | C51: 3.0355362 | D51: 0.38673003
A52: 1.2 | B52: 5107046.1 | C52: 2.9757937 | D52: 0.36424486
A53: 1.3 | B53: 5097751.9 | C53: 2.9183172 | D53: 0.34362683

Sheet المخاطر و SWOT
A1: تحليل SWOT وسجل المخاطر
A2: يُحدَّث عند توفر نتائج التقرير الاستكشافي وعقد البيع
A4: أولاً: تحليل SWOT
A5: م | B5: المحور | E5: البيان
A6: 1 | B6: نقاط القوة | E6: ترخيص تنقيب قائم وطريق مفتوح إلى الموقع؛ كادر عُماني بنسبة تعمين مرتفعة؛ حفارات مستأجرة بالساعة شاملة المشغل والديزل (رأس مال أقل ومرونة)؛ إنتاج كبير نسبياً يحقق وفورات الحجم.
A7: 2 | B7: نقاط الضعف | E7: عدم توفر تقدير معتمد للاحتياطي والدرجة بعد؛ اعتماد على منتج واحد وسعر متقلب؛ الاعتماد على مؤجر الحفارات؛ ارتفاع تكلفة الحفر مع تتبع العروق إلى العمق.
A8: 3 | B8: الفرص | E8: توجه حكومي لرفع إنتاج الكروم إلى 400 ألف طن سنوياً بحلول 2030؛ تسويق موحّد عبر شركة متاجرة المعادن يحسّن القدرة التفاوضية؛ طلب محلي من مصانع المعالجة والفيروكروم (أولوية للسوق المحلي)؛ إمكانية رفع الدرجة بالمعالجة لتحقيق علاوة سعرية.
A9: 4 | B9: التهديدات | E9: شرط 36% لتصدير الخام غير المعالج؛ تقلب أسعار الكروم عالمياً (مرتبطة بسوق الفولاذ المقاوم للصدأ في الصين)؛ طول إجراءات ترخيص التعدين؛ ارتفاع نسبة التعرية مع التعمق؛ تغيّر الرسوم والإتاوات.
A11: ثانياً: سجل المخاطر
A12: م | B12: الخطر | C12: الاحتمال | D12: الأثر | E12: إجراءات التخفيف
A13: 1 | B13: الاحتياطي أو الدرجة أقل من المفترض | C13: متوسط | D13: مرتفع جداً | E13: استكمال برنامج الحفر والعينات وتقرير احتياطي معتمد قبل شراء المعدات؛ البدء بمعدات مستأجرة ثم الشراء بعد تأكيد الخام.
A14: 2 | B14: درجة الخام أقل من 36% (قيد التصدير) | C14: مرتفع | D14: مرتفع | E14: التعاقد المسبق مع مشترٍ محلي أو مع شركة متاجرة المعادن؛ دراسة الفرز/الغسل لرفع الدرجة؛ الحصول على موافقة الوزارة لتصدير الخام المعالج.
A15: 3 | B15: انخفاض سعر الكروم | C15: متوسط | D15: مرتفع | E15: عقود بيع بسعر مرجعي معلن؛ الحفاظ على تكلفة الطن دون سعر التعادل بهامش كافٍ؛ تكوين احتياطي نقدي في السنوات الجيدة.
A16: 4 | B16: ارتفاع نسبة التعرية أو صلابة الصخر | C16: متوسط | D16: مرتفع | E16: خطة تعدين مرحلية تبدأ بالجيوب الأقرب للسطح؛ مراقبة شهرية لنسبة التعرية؛ دراسة بديل التفجير إذا انخفضت إنتاجية الكسارات.
A17: 5 | B17: تأخر ترخيص التعدين أو التصريح البيئي | C17: مرتفع | D17: متوسط | E17: تقديم ملف مكتمل، ومتابعة موافقات الجهات السبع بالتوازي؛ عدم الالتزام بمصاريف ثابتة (إيجارات، توظيف) قبل صدور الترخيص.
A18: 6 | B18: أعطال المعدات وتوقف الإنتاج | C18: متوسط | D18: متوسط | E18: عقد إيجار يُلزم المؤجر بتوفير بديل فوري للحفار المعطل؛ صيانة دورية للشيول والقلاب المملوكين.
A19: 7 | B19: حوادث العمل والسلامة | C19: منخفض | D19: مرتفع | E19: مشرف أمن وسلامة متفرغ؛ تدريب ومعدات وقاية؛ تأمين إصابات العمل؛ ميول آمنة لجدران المحجر.
A20: 8 | B20: الالتزامات البيئية والمجتمعية | C20: منخفض | D20: متوسط | E20: التقيد بالتصريح البيئي، مكافحة الغبار بالرش، إعادة تأهيل تدريجية، وتسديد مساهمة تنمية المجتمع المحلي.
A21: 9 | B21: ضغط السيولة في السنة الأولى | C21: متوسط | D21: متوسط | E21: رأس مال عامل يغطي ثلاثة أشهر؛ فترة سماح للقرض إن أمكن؛ تحصيل سريع لقيمة الشحنات.
A22: 10 | B22: اشتراطات الأعمال تحت السطح عند تتبع العروق | C22: متوسط | D22: مرتفع | E22: تأكيد متطلبات الترخيص والسلامة مع وزارة الطاقة والمعادن؛ تدعيم وتهوية ومراقبة الجدران؛ مراجعة نسب الأعباء الإضافية سنوياً.

Sheet التصحيحات والمصادر
A1: ما تم تصحيحه، ما يحتاج تأكيداً، والمصادر
A2: مقارنة بين الملف الأصلي «دراسة جدوى مقلع كروم» وهذه النسخة المحدثة
A4: أولاً: التصحيحات على الدراسة الأصلية
A5: م | B5: البند | C5: في الملف الأصلي | D5: في النسخة المحدثة | E5: السبب
A6: 1 | B6: الروابط بين الأوراق | C6: روابط إلى ملف خارجي غير موجود (حاسوب آخر) تعطي صفراً | D6: ربط داخلي كامل بين جميع الأوراق | E6: رسوم التراخيص ورأس المال العامل كانت تظهر صفراً بسبب الروابط المكسورة.
A7: 2 | B7: مصاريف ما قبل التشغيل | C7: جدولان مختلفان: 276,220 و332,220 | D7: جدول واحد: 229,392 + ضمانات 55,000 منفصلة | E7: توحيد الأرقام وربط رسوم التراخيص والمأذونيات بأوراقها.
A8: 3 | B8: مصاريف الاستكشاف السابقة | C8: 200,000 في ورقة و257,000 في أخرى | D8: 200,000 (مدخل قابل للتعديل) | E8: يجب تأكيد الرقم الصحيح بالمستندات.
A9: 4 | B9: الضمانات البنكية 55,000 | C9: مصروف ضمن ما قبل التشغيل | D9: وديعة مستردة في نهاية المشروع + عمولة سنوية | E9: الضمان ليس مصروفاً بل نقد محتجز يُسترد بعد إعادة التأهيل.
A10: 5 | B10: رأس المال العامل | C10: صفر | D10: 3 أشهر من التكاليف النقدية | E10: لا يمكن تشغيل المشروع دون سيولة حتى تحصيل أولى المبيعات.
A11: 6 | B11: التأمينات الاجتماعية للعُمانيين | C11: 3,080 ر.ع سنوياً | D11: 14.5% من الرواتب | E11: النسبة النظامية لاشتراك صاحب العمل في صندوق الحماية الاجتماعية.
A12: 7 | B12: اشتراكات ونهاية خدمة الوافدين | C12: غير موجودة | D12: 3% اشتراكات + 9% ادخار/نهاية خدمة | E12: التزامات قانون العمل وقانون الحماية الاجتماعية.
A13: 8 | B13: راتب الحارس | C13: 320 ر.ع | D13: 325 ر.ع | E13: الحد الأدنى لأجور العُمانيين.
A14: 9 | B14: مجموع عمود الراتب الشهري | C14: 5,340 (مجموع رواتب الوحدة) | D14: حُذف | E14: رقم بلا معنى: يجمع راتب الوحدة دون ضرب العدد.
A15: 10 | B15: إيجار الشيول والقلاب | C15: غير مدرج | D15: مضاف في ورقة الإيجارات | E15: الدراسة تتضمن مشغل شيول وسائق قلاب وتذكر استئجارهما في الجدول الزمني دون تكلفة.
A16: 11 | B16: الحفارات | C16: حفار 350 في الجدول الزمني وهيتاشي 240 في الإيجارات | D16: 5 حفارات مستأجرة بالساعة (شاملة المشغل والديزل) + شيول وقلاب وبيك أب مملوكة | E16: معطيات المالك (أكتوبر 2026).
A17: 12 | B17: مأذونيات العمالة الوافدة | C17: 3,420 في ورقة و2,420 في أخرى | D17: محتسبة من رسوم وزارة العمل | E17: حسب فئة المهنة (251 / 201 ر.ع) مع تجديد كل سنتين.
... A22: 17 | B22: الجدول الزمني | C22: بلا تواريخ، والتوظيف والشراء قبل الترخيص | D22: تسلسل: دراسات وتراخيص ← تمويل وتجهيز ← تأهيل ← إنتاج | E22: لتفادي الالتزام بمصاريف ثابتة قبل صدور ترخيص التعدين.
A23: 18 | B23: أخطاء إملائية وتسميات | C23: «عمال صقل أحجار»، «الطاقة والعادن»، «هيئة البية»... | D23: صُححت
A25: ثانياً: بنود يجب تأكيدها قبل اعتماد الدراسة (مرتبة حسب الأثر)
A26: م | B26: البند | C26: القيمة المفترضة | D26: مصدر التأكيد | E26: ملاحظات
A27: 1 | B27: الاحتياطي ودرجة الخام | C27: =TEXT(OreReserve,"#,##0")&" طن بدرجة "&TEXT(OreGrade,"0%") -> 400,000 طن بدرجة 32% | D27: التقرير الاستكشافي ونتائج المختبر | E27: ="أهم مدخل — الإنتاج المستهدف يتطلب "&TEXT('الخطة الفنية والإنتاج'!H26,"#,##0")&" طن خام لخمس سنوات." -> أهم مدخل — الإنتاج المستهدف يتطلب 352,941 طن خام لخمس سنوات.
A28: 2 | B28: نسبة التعرية وإنتاجية التكسير | C28: =TEXT(StripRatio,"0.0")&" طن/طن و"&TEXT(BrkProd,"0")&" طن/ساعة" -> 4.0 طن/طن و35 طن/ساعة | D28: خطة التعدين وتجربة الموقع | E28: تحددان كفاية 5 حفارات لإنتاج 60,000 طن صافٍ — انظر التحقق في «الخطة الفنية والإنتاج».
A29: 3 | B29: سعر البيع والمشتري | C29: ="بيع محلي "&TEXT(LocalShare,"0%")&" بسعر "&TEXT(LocalPrice,"0.00")&" ر.ع/طن" -> بيع محلي 100% بسعر 38.66 ر.ع/طن | D29: عقد أو عرض شراء (شركة متاجرة المعادن / مشترٍ محلي) | E29: يُستبدل الاحتساب بالسعر التعاقدي الفعلي عند توفره.
A30: 4 | B30: نسبة الإتاوة والإيجار السنوي للترخيص | C30: 5% + رسوم سنوية 1,600 | D30: وزارة الطاقة والمعادن | E30: القانون يحدد حداً أدنى؛ النسبة الفعلية تُحدد في الترخيص.
A31: 5 | B31: أسعار المعدات المشتراة | C31: شيول 50,000 + قلاب 32,000 + بيك أب 11,000 ر.ع | D31: عروض أسعار من الوكلاء | E31: افتراض — يُستبدل بعروض الوكلاء.
A32: 6 | B32: أعباء تتبع العروق إلى باطن الأرض | C32: +10% إلى +40% (السنوات 2–5) | D32: خطة التعدين وتجربة الموقع
A33: 7 | B33: مصاريف الاستكشاف السابقة | C33: 200,000 ر.ع | D33: المستندات المحاسبية | E33: الملف الأصلي يذكر أيضاً 257,000.
A34: 8 | B34: شروط التمويل | C34: 150,000 بفائدة 6% لمدة 5 سنوات | D34: الجهة الممولة
A35: 9 | B35: رسوم التراخيص الحالية | C35: 8,400 ر.ع | D35: جداول الرسوم السارية | E35: من الملف الأصلي.
A36: 10 | B36: اشتراكات الحماية الاجتماعية للوافدين | C36: 3% + 9% | D36: صندوق الحماية الاجتماعية | E36: التطبيق مرحلي — يُتحقق من النسب السارية وقت التشغيل.
A38: ثالثاً: المصادر
A39: م | B39: الموضوع | C39: المصدر | E39: الرابط
A40: 1 | B40: أسعار خام الكروم (CIF الصين) | C40: Shanghai Metals Market (SMM) | E40: https://www-old.metal.com/price/Minor-Metals/Chromium
A41: 2 | B41: إنتاج ومبيعات الكروم في السلطنة 2025 | C41: Times of Oman | E41: https://timesofoman.com/article/168275-production-of-chromium-ore-in-oman-exceeded-353000-tonnes-in-2025
A42: 3 | B42: تنظيم تصدير خامي الجبس والكروم | C42: قرار وزاري 18/2025 — وزارة الطاقة والمعادن | E42: https://qanoon.om/p/2025/mem20250018/
A43: 4 | B43: مستهدف 400 ألف طن وشرط 36% | C43: Oman Observer | E43: https://www.omanobserver.om/article/1186906/business/economy/oman-targets-400000-ty-chromite-output-by-2030
A44: 5 | B44: قانون الثروة المعدنية | C44: مرسوم سلطاني 19/2019 | E44: https://qanoon.om/p/2019/rd2019019/
A45: 6 | B45: اشتراكات صندوق الحماية الاجتماعية | C45: Middle East Briefing / Lockton | E45: https://www.middleeastbriefing.com/news/omans-spf-social-security-employer-registration-and-contributions/
A46: 7 | B46: رسوم مأذونيات العمل | C46: Oman Observer — قرار وزارة العمل 602/2025 | E46: https://www.omanobserver.om/article/1178709/oman/labour/mol-issues-decision-on-work-permits-work-practice-permits
A47: 8 | B47: ضريبة الدخل | C47: PwC Worldwide Tax Summaries — Oman | E47: https://taxsummaries.pwc.com/oman/corporate/taxes-on-corporate-income
